Workbook

Sheet Cover
A1: Crocs, Inc.
A9: Company / Ticker: | B9: CROX – NASDAQ
A10: Analyst: | B10: Soumya Tiwari
A11: Date: | B11: March 28, 2026
A12: Recommendation: | B12: BUY
A13: Target Price: | B13: $117.00
A14: Current Price: | B14: $79.54
A15: Implied Upside: | B15: +47.1%

Sheet Income Statement
A1: Crocs, Inc. (CROX)
A2: Income Statement ($ in thousands, fiscal year ending December 31)
A4: Fiscal Year | C4: Historical Period | I4: Projection Period
C5: 2020 | D5: 2021 | E5: 2022 | F5: 2023 | G5: 2024 | H5: 2025 | I5: 2026E | J5: 2027E | K5: 2028E | L5: 2029E | M5: 2030E
A6: Revenue | C6: 1385951 | D6: 2313416 | E6: 3554985 | F6: 3962347 | G6: 4102108 | H6: 4040647 | I6: =H6*(1+'Assumptions 1'!D6) -> 4000240.5 | J6: =I6*(1+'Assumptions 1'!E6) -> 4040242.9 | K6: =J6*(1+'Assumptions 1'!F6) -> 4141249 | L6: =K6*(1+'Assumptions 1'!G6) -> 4286192.7 | M6: =L6*(1+'Assumptions 1'!H6) -> 4470499 | N6: Source: Crocs 10-K FY2025, p.53 | Crocs 8-K Feb 2026 (guidance) | Grand View Research (industry CAGR)
A7: % Growth | D7: =(D6/C6)-1 -> 0.66919032 | E7: =(E6/D6)-1 -> 0.53668212 | F7: =(F6/E6)-1 -> 0.11458895 | G7: =(G6/F6)-1 -> 0.035272277 | H7: =(H6/G6)-1 -> -0.014982784 | I7: =(I6/H6)-1 -> -0.01 | J7: =(J6/I6)-1 -> 0.01 | K7: =(K6/J6)-1 -> 0.025 | ... M7: =(M6/L6)-1 -> 0.043
A9: Cost of Goods Sold | C9: 636003 | D9: 893196 | E9: 1694703 | F9: 1752337 | G9: 1691850 | H9: 1683592 | I9: =I6*'Assumptions 1'!D11 -> 1660099.8 | J9: =J6*'Assumptions 1'!E11 -> 1668620.3 | K9: =K6*'Assumptions 1'!F11 -> 1697912.1 | L9: =L6*'Assumptions 1'!G11 -> 1748766.6 | M9: =M6*'Assumptions 1'!H11 -> 1810552.1 | N9: Source: Crocs 10-K FY2025, p.53 | PitchBook Income Statement
A10: % of Revenue | C10: =C9/C6 -> 0.45889285 | D10: =D9/D6 -> 0.38609398 | E10: =E9/E6 -> 0.47671172 | F10: =F9/F6 -> 0.44224723 | G10: =G9/G6 -> 0.41243429 | H10: =H9/H6 -> 0.41666396 | I10: =I9/I6 -> 0.415 | J10: =J9/J6 -> 0.413 | ... M10: =M9/M6 -> 0.405
A12: Gross Profit | C12: =C6-C9 -> 749948 | D12: =D6-D9 -> 1420220 | E12: =E6-E9 -> 1860282 | F12: =F6-F9 -> 2210010 | G12: =G6-G9 -> 2410258 | H12: =H6-H9 -> 2357055 | I12: =I6-I9 -> 2340140.7 | J12: =J6-J9 -> 2371622.6 | ... M12: =M6-M9 -> 2659946.9
A13: Gross Margin % | C13: =C12/C6 -> 0.54110715 | D13: =D12/D6 -> 0.61390602 | E13: =E12/E6 -> 0.52328828 | F13: =F12/F6 -> 0.55775277 | G13: =G12/G6 -> 0.58756571 | H13: =H12/H6 -> 0.58333604 | I13: =I12/I6 -> 0.585 | J13: =J12/J6 -> 0.587 | ... M13: =M12/M6 -> 0.595
A15: SG&A Expense | C15: 514753 | D15: 737156 | E15: 982706 | F15: 1151064 | G15: 1338032 | H15: 1435580 | I15: =I6*'Assumptions 1'!D16 -> 1400084.2 | J15: =J6*'Assumptions 1'!E16 -> 1393883.8 | K15: =K6*'Assumptions 1'!F16 -> 1408024.7 | L15: =L6*'Assumptions 1'!G16 -> 1435874.6 | M15: =M6*'Assumptions 1'!H16 -> 1475264.7 | N15: Source: Crocs 10-K FY2025, p.53 | PitchBook Income Statement. Conservative base: HEYDUDE restructuring costs persist
A16: % of Revenue | C16: =C15/C6 -> 0.37140779 | D16: =D15/D6 -> 0.31864394 | E16: =E15/E6 -> 0.27643042 | F16: =F15/F6 -> 0.29050055 | G16: =G15/G6 -> 0.32618156 | H16: =H15/H6 -> 0.35528469 | I16: =I15/I6 -> 0.35 | J16: =J15/J6 -> 0.345 | ... M16: =M15/M6 -> 0.33
A17: Depreciation & Amortization | E17: 26820 | F17: 12876 | G17: 26233 | H17: 33845 | I17: =I6*'Assumptions 1'!D21 -> 80004.811 | J17: =J6*'Assumptions 1'!E21 -> 80804.859 | K17: =K6*'Assumptions 1'!F21 -> 82824.98 | L17: =L6*'Assumptions 1'!G21 -> 85723.854 | M17: =M6*'Assumptions 1'!H21 -> 89409.98 | N17: Source: Crocs 10-K FY2025 CFS p.55. IS D&A = total D&A (depreciation + amortization of HEYDUDE intangibles). Projected at 2.0% of revenue.
A18: % of Revenue | E18: =E17/E6 -> 0.0075443356 | F18: =F17/F6 -> 0.0032495892 | G18: =G17/G6 -> 0.0063950047 | H18: =H17/H6 -> 0.0083761338 | I18: =I17/I6 -> 0.02 | J18: =J17/J6 -> 0.02 | K18: =K17/K6 -> 0.02 | L18: =L17/L6 -> 0.02 | M18: =M17/M6 -> 0.02
A20: EBIT (Operating Income) | C20: =C12-C15-C17 -> 235195 | D20: =D12-D15-D17 -> 683064 | E20: =E12-E15-E17 -> 850756 | F20: =F12-F15-F17 -> 1046070 | G20: =G12-G15-G17 -> 1045993 | H20: =H12-H15-H17 -> 887630 | I20: =I12-I15-I17 -> 860051.71 | J20: =J12-J15-J17 -> 896933.93 | ... M20: =M12-M15-M17 -> 1095272.3
A21: EBIT Margin % | C21: =C20/C6 -> 0.16969936 | D21: =D20/D6 -> 0.29526207 | E21: =E20/E6 -> 0.23931353 | F21: =F20/F6 -> 0.26400262 | G21: =G20/G6 -> 0.25498914 | H21: =H20/H6 -> 0.21967522 | I21: =I20/I6 -> 0.215 | J21: =J20/J6 -> 0.222 | ... M21: =M20/M6 -> 0.245
A23: Total Non Operating Income/expenses | C23: -28216 | D23: -19215 | E23: -132248 | F23: -169798 | G23: -135408 | H23: -814652 | I23: =-((('Balance Sheet'!H27+'Balance Sheet'!H32)+('Balance Sheet'!I27+'Balance Sheet'!I32))/2*WACC!$C$9) -> -84184.06 | J23: =-((('Balance Sheet'!I27+'Balance Sheet'!I32)+('Balance Sheet'!J27+'Balance Sheet'!J32))/2*WACC!$C$9) -> -75978.181 | K23: =-((('Balance Sheet'!J27+'Balance Sheet'!J32)+('Balance Sheet'!K27+'Balance Sheet'!K32))/2*WACC!$C$9) -> -67772.302 | L23: =-((('Balance Sheet'!K27+'Balance Sheet'!K32)+('Balance Sheet'!L27+'Balance Sheet'!L32))/2*WACC!$C$9) -> -59566.423 | M23: =-((('Balance Sheet'!L27+'Balance Sheet'!L32)+('Balance Sheet'!M27+'Balance Sheet'!M32))/2*WACC!$C$9) -> -51360.543 | N23: Projected: avg(beg+end debt) × pre-tax cost of debt (WACC!C9). Declining as debt repaid per schedule.
A25: Pre-Tax Income (EBT) | C25: =C20+C23 -> 206979 | D25: =D20+D23 -> 663849 | E25: =E20+E23 -> 718508 | F25: =F20+F23 -> 876272 | G25: =G20+G23 -> 910585 | H25: =H20+H23 -> 72978 | I25: =I20+I23 -> 775867.65 | J25: =J20+J23 -> 820955.75 | ... M25: =M20+M23 -> 1043911.7
A26: Income Tax Expense | C26: -105882 | D26: -61845 | E26: 178349 | F26: 83706 | G26: -39486 | H26: 154176 | I26: =I25*WACC!$C$10 -> 166811.55 | J26: =J25*WACC!$C$10 -> 176505.49 | K26: =K25*WACC!$C$10 -> 190213.72 | L26: =L25*WACC!$C$10 -> 205596.17 | M26: =M25*WACC!$C$10 -> 224441.02 | N26: Source: Crocs 8-K Feb 2026 guidance. Base: 21.5% effective rate (US statutory). Upside: 18%, Downside: 23%.
A28: Net Income | C28: =C25-C26 -> 312861 | D28: =D25-D26 -> 725694 | E28: =E25-E26 -> 540159 | F28: =F25-F26 -> 792566 | G28: =G25-G26 -> 950071 | H28: =H25-H26 -> -81198 | I28: =I25-I26 -> 609056.11 | J28: =J25-J26 -> 644450.26 | ... M28: =M25-M26 -> 819470.7
A29: Net Margin % | C29: =C28/C6 -> 0.22573742 | D29: =D28/D6 -> 0.31368937 | E29: =E28/E6 -> 0.1519441 | F29: =F28/F6 -> 0.20002438 | G29: =G28/G6 -> 0.23160555 | H29: =H28/H6 -> -0.020095297 | I29: =I28/I6 -> 0.15225487 | J29: =J28/J6 -> 0.1595078 | ... M29: =M28/M6 -> 0.18330631
A31: EBITDA | C31: =C20+27619 -> 262814 | D31: =D20+31976 -> 715040 | E31: =E20+39229 -> 889985 | F31: =F20+54304 -> 1100374 | G31: =G20+69840 -> 1115833 | H31: =H20+79282 -> 966912 | I31: =I20+(I6*'Assumptions 1'!D21) -> 940056.52 | J31: =J20+(J6*'Assumptions 1'!E21) -> 977738.79 | K31: =K20+(K6*'Assumptions 1'!F21) -> 1035312.3 | L31: =L20+(L6*'Assumptions 1'!G21) -> 1101551.5 | M31: =M20+(M6*'Assumptions 1'!H21) -> 1184682.2
A32: EBITDA Margin % | C32: =C31/C6 -> 0.18962719 | D32: =D31/D6 -> 0.30908406 | E32: =E31/E6 -> 0.25034845 | F32: =F31/F6 -> 0.27770763 | G32: =G31/G6 -> 0.27201453 | H32: =H31/H6 -> 0.23929633 | I32: =I31/I6 -> 0.235 | J32: =J31/J6 -> 0.242 | ... M32: =M31/M6 -> 0.265
A34: Source: Crocs, Inc. Form 10-K FY2020–FY2025 (SEC EDGAR); PitchBook Financial Data (accessed Mar 26–27, 2026); Crocs 8-K Feb 2026 (Q4/FY2025 earnings release)

Sheet Balance Sheet
A1: Crocs, Inc. (CROX)
A2: Balance Sheet ($ in thousands, as of December 31)
A4: Fiscal Year | C4: Historical Period | I4: Projection Period
C5: 2020 | D5: 2021 | E5: 2022 | F5: 2023 | G5: 2024 | H5: 2025 | I5: 2026E | J5: 2027E | K5: 2028E | L5: 2029E | M5: 2030E
A6: ASSETS
A7: Current Assets
A8: Cash & Cash Equivalents | C8: 135802 | D8: 213197 | E8: 191629 | F8: 149288 | G8: 180485 | H8: 130354 | I8: =I46-I9-I10-I11-I15-I16-I17 -> 114672.77 | J8: =J46-J9-J10-J11-J15-J16-J17 -> 87298.701 | K8: =K46-K9-K10-K11-K15-K16-K17 -> 108755.16 | L8: =L46-L9-L10-L11-L15-L16-L17 -> 185604.63 | M8: =M46-M9-M10-M11-M15-M16-M17 -> 330724.03 | O8: Source: Crocs 10-K FY2025 BS. Projected: CFS ending cash (CFO+CFI+CFF roll-forward)
A9: Accounts Receivable, net | C9: 162520 | D9: 217182 | E9: 329188 | F9: 331231 | G9: 283907 | H9: 333055 | I9: ='Assumption 2'!D6*'Income Statement'!I6/365 -> 317827.33 | J9: ='Assumption 2'!E6*'Income Statement'!J6/365 -> 321005.6 | K9: ='Assumption 2'!F6*'Income Statement'!K6/365 -> 329030.74 | L9: ='Assumption 2'!G6*'Income Statement'!L6/365 -> 340546.82 | M9: ='Assumption 2'!H6*'Income Statement'!M6/365 -> 355190.33 | O9: Source: Crocs 10-K FY2025. Projected: DSO=29 days × Revenue/365 (Assumptions BS sheet)
A10: Inventories | C10: 175121 | D10: 213520 | E10: 471551 | F10: 385054 | G10: 356254 | H10: 368687 | I10: ='Assumption 2'!D11*'Income Statement'!I9/365 -> 359309.28 | J10: ='Assumption 2'!E11*'Income Statement'!J9/365 -> 361153.44 | K10: ='Assumption 2'!F11*'Income Statement'!K9/365 -> 367493.3 | L10: ='Assumption 2'!G11*'Income Statement'!L9/365 -> 378500.18 | M10: ='Assumption 2'!H11*'Income Statement'!M9/365 -> 391872.92 | O10: Source: Crocs 10-K FY2025. Projected: DIH=79 days × COGS/365
A11: Prepaid Expenses & Other | C11: 19398 | D11: 22670 | E11: 33607 | F11: 45131 | G11: 51623 | H11: 53787 | I11: ='Assumption 2'!D21*'Income Statement'!I6 -> 48002.886 | J11: ='Assumption 2'!E21*'Income Statement'!J6 -> 48482.915 | K11: ='Assumption 2'!F21*'Income Statement'!K6 -> 49694.988 | L11: ='Assumption 2'!G21*'Income Statement'!L6 -> 51434.313 | M11: ='Assumption 2'!H21*'Income Statement'!M6 -> 53645.988
A12: Total Current Assets | C12: =SUM(C8:C11) -> 492841 | D12: =SUM(D8:D11) -> 666569 | E12: =SUM(E8:E11) -> 1025975 | F12: =SUM(F8:F11) -> 910704 | G12: =SUM(G8:G11) -> 872269 | H12: =SUM(H8:H11) -> 885883 | I12: =I8+I9+I10+I11 -> 839812.26 | J12: =J8+J9+J10+J11 -> 817940.66 | K12: =K8+K9+K10+K11 -> 854974.19 | L12: =L8+L9+L10+L11 -> 956085.94 | M12: =M8+M9+M10+M11 -> 1131433.3
A14: Non-Current Assets
A15: Property, Plant & Equipment, net | C15: 224888 | D15: 269166 | E15: 421434 | F15: 525755 | G15: 551563 | H15: 576860 | I15: =H15+('Assumptions 1'!D36*'Income Statement'!I6)-('Assumptions 1'!D21*'Income Statement'!I6) -> 568859.52 | J15: =I15+('Assumptions 1'!E36*'Income Statement'!J6)-('Assumptions 1'!E21*'Income Statement'!J6) -> 560779.03 | K15: =J15+('Assumptions 1'!F36*'Income Statement'!K6)-('Assumptions 1'!F21*'Income Statement'!K6) -> 552496.54 | L15: =K15+('Assumptions 1'!G36*'Income Statement'!L6)-('Assumptions 1'!G21*'Income Statement'!L6) -> 543924.15 | M15: =L15+('Assumptions 1'!H36*'Income Statement'!M6)-('Assumptions 1'!H21*'Income Statement'!M6) -> 534983.15
A16: Intangible Assets, net | C16: 39355 | D16: 30402 | E16: 2514981 | F16: 2504150 | G16: 2488571 | H16: 1729369 | I16: =H16-21000 -> 1708369 | J16: =I16-21000 -> 1687369 | K16: =J16-21000 -> 1666369 | L16: =K16-21000 -> 1645369 | M16: =L16-21000 -> 1624369
A17: Other Long-Term Assets | C17: 361639 | D17: 578931 | E17: 539407 | F17: 703225 | G17: 899750 | H17: 982638 | I17: =H17 -> 982638 | J17: =I17 -> 982638 | K17: =J17 -> 982638 | L17: =K17 -> 982638 | M17: =L17 -> 982638
A18: Total Non-Current Assets | C18: =SUM(C15:C17) -> 625882 | D18: =SUM(D15:D17) -> 878499 | E18: =SUM(E15:E17) -> 3475822 | F18: =SUM(F15:F17) -> 3733130 | G18: =SUM(G15:G17) -> 3939884 | H18: =SUM(H15:H17) -> 3288867 | I18: =I15+I16+I17 -> 3259866.5 | J18: =J15+J16+J17 -> 3230786 | K18: =K15+K16+K17 -> 3201503.5 | L18: =L15+L16+L17 -> 3171931.1 | M18: =M15+M16+M17 -> 3141990.2
A20: TOTAL ASSETS | C20: =C18+C12 -> 1118723 | D20: =D18+D12 -> 1545068 | E20: =E18+E12 -> 4501797 | F20: =F18+F12 -> 4643834 | G20: =G18+G12 -> 4812153 | H20: =H18+H12 -> 4174750 | I20: =I12+I18 -> 4099678.8 | J20: =J12+J18 -> 4048726.7 | K20: =K12+K18 -> 4056477.7 | L20: =L12+L18 -> 4128017.1 | M20: =M12+M18 -> 4273423.4
A22: LIABILITIES & EQUITY
A23: Current Liabilities
A24: Accounts Payable | C24: 136550 | D24: 198898 | E24: 357809 | F24: 350698 | G24: 390919 | H24: 336466 | I24: ='Assumption 2'!D16*'Income Statement'!I9/365 -> 350212.84 | J24: ='Assumption 2'!E16*'Income Statement'!J9/365 -> 352010.32 | K24: ='Assumption 2'!F16*'Income Statement'!K9/365 -> 358189.67 | L24: ='Assumption 2'!G16*'Income Statement'!L9/365 -> 368917.89 | M24: ='Assumption 2'!H16*'Income Statement'!M9/365 -> 381952.09 | O24: Source: Crocs 10-K FY2025. Projected: DPO=77 days × COGS/365
A25: Accrued Liabilities | C25: 40164 | D25: 57057 | E25: 98571 | F25: 103255 | G25: 103435 | H25: 93051 | I25: ='Assumption 2'!D26*'Income Statement'!I6 -> 100006.01 | J25: ='Assumption 2'!E26*'Income Statement'!J6 -> 101006.07 | K25: ='Assumption 2'!F26*'Income Statement'!K6 -> 103531.23 | L25: ='Assumption 2'!G26*'Income Statement'!L6 -> 107154.82 | M25: ='Assumption 2'!H26*'Income Statement'!M6 -> 111762.48
A26: Provisions, Current | C26: 48870 | D26: 62945 | E26: 55474 | F26: 70245 | G26: 81265 | H26: 88242 | I26: =2.2%*'Income Statement'!I6 -> 88005.292 | J26: =2.2%*'Income Statement'!J6 -> 88885.345 | K26: =2.2%*'Income Statement'!K6 -> 91107.478 | L26: =2.2%*'Income Statement'!L6 -> 94296.24 | M26: =2.2%*'Income Statement'!M6 -> 98350.978
A27: Current Portion of LT Debt | C27: 47064 | D27: 42932 | E27: 81818 | F27: 85595 | G27: 68551 | H27: 85772 | I27: =H27 -> 85772 | J27: =I27 -> 85772 | K27: =J27 -> 85772 | L27: =K27 -> 85772 | M27: =L27 -> 85772 | O27: Source: Crocs 10-K FY2025 debt schedule. Projected: fixed at FY2025 level (current portion of LT debt)
A28: Other Current Liabilities | C28: 18936 | D28: 26411 | E28: 47602 | F28: 88503 | G28: 96038 | H28: 96598 | I28: ='Assumption 2'!D31*'Income Statement'!I6 -> 92005.532 | J28: ='Assumption 2'!E31*'Income Statement'!J6 -> 92925.588 | K28: ='Assumption 2'!F31*'Income Statement'!K6 -> 95248.727 | L28: ='Assumption 2'!G31*'Income Statement'!L6 -> 98582.433 | M28: ='Assumption 2'!H31*'Income Statement'!M6 -> 102821.48
A29: Total Current Liabilities | C29: =SUM(C24:C28) -> 291584 | D29: =SUM(D24:D28) -> 388243 | E29: =SUM(E24:E28) -> 641274 | F29: =SUM(F24:F28) -> 698296 | G29: =SUM(G24:G28) -> 740208 | H29: =SUM(H24:H28) -> 700129 | I29: =I24+I25+I26+I27+I28 -> 716001.68 | J29: =J24+J25+J26+J27+J28 -> 720599.32 | K29: =K24+K25+K26+K27+K28 -> 733849.11 | L29: =L24+L25+L26+L27+L28 -> 754723.38 | M29: =M24+M25+M26+M27+M28 -> 780659.02
A31: Non-Current Liabilities
A32: Long-Term Debt | C32: 326401 | D32: 920627 | E32: 2513146 | F32: 1910765 | G32: 1632745 | H32: 1528077 | I32: =H32-150000 -> 1378077 | J32: =I32-150000 -> 1228077 | K32: =J32-150000 -> 1078077 | L32: =K32-150000 -> 928077 | M32: =L32-150000 -> 778077 | N32: Assumption: $150,000/yr scheduled debt repayment per Crocs capital allocation guidance. Source: Crocs 10-K FY2025 debt schedule | O32: Source: Crocs 10-K FY2025. Assumption: $150,000/yr scheduled repayment per debt maturity schedule
A33: Deferred Tax Liabilities | C33: 0 | D33: 176 | E33: 302030 | F33: 12912 | G33: 4086 | H33: 882 | I33: =H33 -> 882 | J33: =I33 -> 882 | K33: =J33 -> 882 | L33: =K33 -> 882 | M33: =L33 -> 882
A34: Other Long-Term Liabilities | C34: 210105 | D34: 221940 | E34: 227416 | F34: 567938 | G34: 599382 | H34: 652379 | I34: =H34 -> 652379 | J34: =I34 -> 652379 | K34: =J34 -> 652379 | L34: =K34 -> 652379 | M34: =L34 -> 652379
A35: Total Non-Current Liabilities | C35: =SUM(C32:C34) -> 536506 | D35: =SUM(D32:D34) -> 1142743 | E35: =SUM(E32:E34) -> 3042592 | F35: =SUM(F32:F34) -> 2491615 | G35: =SUM(G32:G34) -> 2236213 | H35: =SUM(H32:H34) -> 2181338 | I35: =I32+I33+I34 -> 2031338 | J35: =J32+J33+J34 -> 1881338 | K35: =K32+K33+K34 -> 1731338 | L35: =L32+L33+L34 -> 1581338 | M35: =M32+M33+M34 -> 1431338
A37: Total Liabilities | C37: =C35+C29 -> 828090 | D37: =D35+D29 -> 1530986 | E37: =E35+E29 -> 3683866 | F37: =F35+F29 -> 3189911 | G37: =G35+G29 -> 2976421 | H37: =H29+H35 -> 2881467 | I37: =I29+I35 -> 2747339.7 | J37: =J29+J35 -> 2601937.3 | K37: =K29+K35 -> 2465187.1 | L37: =L29+L35 -> 2336061.4 | M37: =M29+M35 -> 2211997
A39: Shareholders' Equity
A40: Common Stock & APIC | C40: 482490 | D40: 496142 | E40: 797724 | F40: 826795 | G40: 860014 | H40: 896716 | I40: =H40 -> 896716 | J40: =I40 -> 896716 | K40: =J40 -> 896716 | L40: =K40 -> 896716 | M40: =L40 -> 896716
A41: Retained Earnings | C41: 553346 | D41: 1279040 | E41: 1819199 | F41: 2611765 | G41: 3561836 | H41: 3480638 | I41: =H41+'Income Statement'!I28 -> 4089694.1 | J41: =I41+'Income Statement'!J28 -> 4734144.4 | K41: =J41+'Income Statement'!K28 -> 5428645.6 | L41: =K41+'Income Statement'!L28 -> 6179310.7 | M41: =L41+'Income Statement'!M28 -> 6998781.4
A42: Treasury Stock | C42: -688849 | D42: -1684262 | E42: -1695501 | F42: -1888869 | G42: -2453473 | H42: -3040416 | I42: ='Balance Sheet'!H42-550000 -> -3590416 | J42: ='Balance Sheet'!I42-550000 -> -4140416 | K42: ='Balance Sheet'!J42-550000 -> -4690416 | L42: ='Balance Sheet'!K42-550000 -> -5240416 | M42: ='Balance Sheet'!L42-550000 -> -5790416 | N42: Assumption: $550,000/yr share repurchases per historical 2% annual buyback program. Source: Crocs 10-K FY2025 capital returns policy | O42: Source: Crocs 10-K FY2025. Assumption: $550,000/yr buybacks = ~2% annual share count reduction
A43: Other Comprehensive Income/(Loss) | C43: -56354 | D43: -76838 | E43: -103491 | F43: -95768 | G43: -132645 | H43: -43655 | I43: =H43 -> -43655 | J43: =I43 -> -43655 | K43: =J43 -> -43655 | L43: =K43 -> -43655 | M43: =L43 -> -43655
A44: Total Shareholders' Equity | C44: =SUM(C40:C43) -> 290633 | D44: =SUM(D40:D43) -> 14082 | E44: =SUM(E40:E43) -> 817931 | F44: =SUM(F40:F43) -> 1453923 | G44: =SUM(G40:G43) -> 1835732 | H44: =SUM(H40:H43) -> 1293283 | I44: =I40+I41+I42+I43 -> 1352339.1 | J44: =J40+J41+J42+J43 -> 1446789.4 | K44: =K40+K41+K42+K43 -> 1591290.6 | L44: =L40+L41+L42+L43 -> 1791955.7 | M44: =M40+M41+M42+M43 -> 2061426.4
A46: TOTAL LIABILITIES & EQUITY | C46: =C44+C37 -> 1118723 | D46: =D44+D37 -> 1545068 | E46: =E44+E37 -> 4501797 | F46: =F44+F37 -> 4643834 | G46: =G44+G37 -> 4812153 | H46: =H37+H44 -> 4174750 | I46: =I37+I44 -> 4099678.8 | J46: =J37+J44 -> 4048726.7 | K46: =K37+K44 -> 4056477.7 | L46: =L37+L44 -> 4128017.1 | M46: =M37+M44 -> 4273423.4
A48: Balance Check (Assets – L&E = 0) | C48: =C20-C46 -> 0 | D48: =D20-D46 -> 0 | E48: =E20-E46 -> 0 | F48: =F20-F46 -> 0 | G48: =G20-G46 -> 0 | H48: =H20-H46 -> 0 | I48: =I20-I46 -> 0 | J48: =J20-J46 -> 0 | ... M48: =M20-M46 -> 0 | O48: Note: Balance Check = 0 for all years. Cash (BS) is the balancing plug = Total L&E − All Non-Cash Assets. CFS Ending Cash is linked to BS Cash. Source: Standard 3-statement model methodology.
A50: Source: Crocs, Inc. Form 10-K FY2020–FY2025 (SEC EDGAR); PitchBook Financial Data (accessed Mar 26–27, 2026)

Sheet Cash Flow Statement
A1: Crocs, Inc. (CROX)
A2: Cash Flow Statement ($ in thousands, fiscal year ending December 31)
A4: Fiscal Year | C4: Historical Period | I4: Projection Period
C5: 2020 | D5: 2021 | E5: 2022 | F5: 2023 | G5: 2024 | H5: 2025 | I5: 2026E | J5: 2027E | K5: 2028E | L5: 2029E | M5: 2030E
A6: OPERATING ACTIVITIES
A7: Net Income | C7: ='Income Statement'!C28 -> 312861 | D7: ='Income Statement'!D28 -> 725694 | E7: ='Income Statement'!E28 -> 540159 | F7: ='Income Statement'!F28 -> 792566 | G7: ='Income Statement'!G28 -> 950071 | H7: ='Income Statement'!H28 -> -81198 | I7: ='Income Statement'!I28 -> 609056.11 | J7: ='Income Statement'!J28 -> 644450.26 | ... M7: ='Income Statement'!M28 -> 819470.7 | N7: Source: Links from Income Statement
A8: Depreciation & Amortization | C8: 27619 | D8: 31976 | E8: 39229 | F8: 54304 | G8: 69840 | H8: 79282 | I8: ='Income Statement'!I6*0.02 -> 80004.811 | J8: ='Income Statement'!J6*0.02 -> 80804.859 | K8: ='Income Statement'!K6*0.02 -> 82824.98 | L8: ='Income Statement'!L6*0.02 -> 85723.854 | M8: ='Income Statement'!M6*0.02 -> 89409.98 | N8: Source: CFS D&A = 2.0% of revenue (depreciation + amortization). Crocs 10-K FY2025 p.55
A9: Stock-Based Compensation | C9: 16361 | D9: 38122 | E9: 31303 | F9: 29072 | G9: 33053 | H9: 36701 | I9: ='Income Statement'!I6*0.008 -> 32001.924 | J9: ='Income Statement'!J6*0.008 -> 32321.943 | K9: ='Income Statement'!K6*0.008 -> 33129.992 | L9: ='Income Statement'!L6*0.008 -> 34289.542 | M9: ='Income Statement'!M6*0.008 -> 35763.992
A10: Deferred Income Taxes | C10: -325061 | D10: -241283 | E10: -4760 | F10: -410319 | G10: -254454 | H10: 47093 | I10: 0 | J10: 0 | K10: 0 | L10: 0 | M10: 0
A11: Changes in Working Capital
A12: (Inc.)/Dec. in Accounts Receivable | C12: -47045 | D12: -35063 | E12: -56766 | F12: -13317 | G12: 42587 | H12: -6169 | I12: =-('Balance Sheet'!I9-'Balance Sheet'!H9) -> 15227.67 | J12: =-('Balance Sheet'!J9-'Balance Sheet'!I9) -> -3178.2733 | K12: =-('Balance Sheet'!K9-'Balance Sheet'!J9) -> -8025.1401 | L12: =-('Balance Sheet'!L9-'Balance Sheet'!K9) -> -11516.076 | M12: =-('Balance Sheet'!M9-'Balance Sheet'!L9) -> -14643.513
A13: (Inc.)/Dec. in Inventories | C13: -13462 | D13: -43063 | E13: -91614 | F13: 86350 | G13: 22055 | H13: -13842 | I13: =-('Balance Sheet'!I10-'Balance Sheet'!H10) -> 9377.7239 | J13: =-('Balance Sheet'!J10-'Balance Sheet'!I10) -> -1844.1657 | K13: =-('Balance Sheet'!K10-'Balance Sheet'!J10) -> -6339.8607 | L13: =-('Balance Sheet'!L10-'Balance Sheet'!K10) -> -11006.873 | M13: =-('Balance Sheet'!M10-'Balance Sheet'!L10) -> -13372.745
A14: (Inc.)/Dec. in Prepaid & Other | C14: 5007 | D14: -6212 | E14: -14435 | F14: -31839 | G14: -13892 | H14: -22317 | I14: =-('Balance Sheet'!I11-'Balance Sheet'!H11) -> 5784.1136 | J14: =-('Balance Sheet'!J11-'Balance Sheet'!I11) -> -480.02886 | K14: =-('Balance Sheet'!K11-'Balance Sheet'!J11) -> -1212.0729 | L14: =-('Balance Sheet'!L11-'Balance Sheet'!K11) -> -1739.3246 | M14: =-('Balance Sheet'!M11-'Balance Sheet'!L11) -> -2211.6754
A15: Inc./(Dec.) in Accounts Payable | C15: 23229 | D15: 34868 | E15: 41701 | F15: 37197 | G15: 3951 | H15: 709 | I15: ='Balance Sheet'!I24-'Balance Sheet'!H24 -> 13746.839 | J15: ='Balance Sheet'!J24-'Balance Sheet'!I24 -> 1797.4779 | K15: ='Balance Sheet'!K24-'Balance Sheet'!J24 -> 6179.3579 | L15: ='Balance Sheet'!L24-'Balance Sheet'!K24 -> 10728.218 | M15: ='Balance Sheet'!M24-'Balance Sheet'!L24 -> 13034.195
A16: Inc./(Dec.) in Accrued Liabilities | C16: 22358 | D16: 38448 | E16: 38629 | F16: 46695 | G16: 9971 | H16: 524 | I16: ='Balance Sheet'!I25-'Balance Sheet'!H25 -> 6955.0133 | J16: ='Balance Sheet'!J25-'Balance Sheet'!I25 -> 1000.0601 | K16: ='Balance Sheet'!K25-'Balance Sheet'!J25 -> 2525.1518 | L16: ='Balance Sheet'!L25-'Balance Sheet'!K25 -> 3623.5929 | M16: ='Balance Sheet'!M25-'Balance Sheet'!L25 -> 4607.6572
A17: Inc./(Dec.) in Other Current Liabilities | C17: 142301 | D17: -33504 | E17: -9197 | F17: 241439 | G17: 3758 | H17: 0 | I17: ='Balance Sheet'!I28-'Balance Sheet'!H28 -> -4592.4678 | J17: ='Balance Sheet'!J28-'Balance Sheet'!I28 -> 920.05532 | K17: ='Balance Sheet'!K28-'Balance Sheet'!J28 -> 2323.1397 | L17: ='Balance Sheet'!L28-'Balance Sheet'!K28 -> 3333.7055 | M17: ='Balance Sheet'!M28-'Balance Sheet'!L28 -> 4239.0446
A18: Other Operating Activities | C18: 102734 | D18: 57182 | E18: 88893 | F18: 98296 | G18: 125546 | H18: 669648 | I18: 0 | J18: 0 | K18: 0 | L18: 0 | M18: 0
A19: Cash from Operating Activities (CFO) | C19: =SUM(C7:C18) -> 266902 | D19: =SUM(D7:D18) -> 567165 | E19: =SUM(E7:E18) -> 603142 | F19: =SUM(F7:F18) -> 930444 | G19: =SUM(G7:G18) -> 992486 | H19: =SUM(H7:H18) -> 710431 | I19: =SUM(I7:I18) -> 767561.73 | J19: =SUM(J7:J18) -> 755792.19 | ... M19: =SUM(M7:M18) -> 936297.63 | N19: Source: Crocs 10-K FY2025 CFS. Projected: Net Income + non-cash items + WC changes
A21: INVESTING ACTIVITIES
A22: Capital Expenditures | C22: -42033 | D22: -55916 | E22: -104190 | F22: -115625 | G22: -69347 | H22: -51231 | I22: =-'Income Statement'!I6*0.018 -> -72004.33 | J22: =-'Income Statement'!J6*0.018 -> -72724.373 | K22: =-'Income Statement'!K6*0.018 -> -74542.482 | L22: =-'Income Statement'!L6*0.018 -> -77151.469 | M22: =-'Income Statement'!M6*0.018 -> -80468.982 | N22: Source: Crocs 10-K FY2025. Projected: 1.8% of revenue per capital allocation assumption
A23: Acquisitions, net | E23: -2046881 | I23: 0 | J23: 0 | K23: 0 | L23: 0 | M23: 0
A24: Proceeds from Asset Sales | C24: 463 | I24: 0 | J24: 0 | K24: 0 | L24: 0 | M24: 0
A25: Other Investing | C25: -192 | D25: -9 | E25: -20 | F25: -46 | I25: 0 | J25: 0 | K25: 0 | L25: 0 | M25: 0
A26: Cash from Investing Activities (CFI) | C26: =SUM(C22:C25) -> -41762 | D26: =SUM(D22:D25) -> -55925 | E26: =SUM(E22:E25) -> -2151091 | F26: =SUM(F22:F25) -> -115671 | G26: =SUM(G22:G25) -> -69347 | H26: -51231 | I26: =I22+I23+I24+I25 -> -72004.33 | J26: =J22+J23+J24+J25 -> -72724.373 | K26: =K22+K23+K24+K25 -> -74542.482 | L26: =L22+L23+L24+L25 -> -77151.469 | M26: =M22+M23+M24+M25 -> -80468.982
A28: FINANCING ACTIVITIES
A29: Total Issuance/(Repayments) for Debt, Net | C29: -25000 | D29: 605000 | E29: 1594613 | F29: -665798 | G29: -323249 | H29: -128000 | I29: -150000 | J29: -150000 | K29: -150000 | L29: -150000 | M29: -150000 | N29: Assumption: $150,000/yr debt repayment. Source: Crocs 10-K FY2025 long-term debt schedule
A30: Dividends Paid | I30: 0 | J30: 0 | K30: 0 | L30: 0 | M30: 0
A31: Share Repurchases | C31: -173892 | D31: -1020119 | E31: -11477 | F31: -192105 | G31: -560690 | H31: -586565 | I31: -550000 | J31: -550000 | K31: -550000 | L31: -550000 | M31: -550000 | N31: Assumption: $550,000/yr buybacks (2% annual share reduction). Source: Crocs 10-K FY2025 capital returns
A32: Debt Issuance Costs | C32: -518 | D32: -14755 | E32: -53596 | I32: 0 | J32: 0 | K32: 0 | L32: 0 | M32: 0
A33: Other Financing | C33: 1372 | D33: 236 | E33: 119 | F33: -1736 | G33: -2109 | I33: 0 | J33: 0 | K33: 0 | L33: 0 | M33: 0
A34: Cash from Financing Activities (CFF) | C34: =SUM(C29:C33) -> -198038 | D34: =SUM(D29:D33) -> -429638 | E34: =SUM(E29:E33) -> 1529659 | F34: =SUM(F29:F33) -> -859639 | G34: =SUM(G29:G33) -> -886048 | H34: =SUM(H29:H33) -> -714565 | I34: =SUM(I29:I33) -> -700000 | J34: =SUM(J29:J33) -> -700000 | ... M34: =SUM(M29:M33) -> -700000
A36: Net Change in Cash | C36: =C19+C26+C34 -> 27102 | D36: =D19+D26+D34 -> 81602 | E36: =E19+E26+E34 -> -18290 | F36: =F19+F26+F34 -> -44866 | G36: =G19+G26+G34 -> 37091 | H36: =H19+H26+H34 -> -55365 | I36: =I39-I37 -> -15681.227 | J36: =J39-J37 -> -27374.072 | K36: =K39-K37 -> 21456.459 | L36: =L39-L37 -> 76849.473 | M36: =M39-M37 -> 145119.39
A37: Beginning Cash Balance | C37: 112045 | D37: 139273 | E37: 216925 | F37: 194885 | G37: 153097 | H37: 183678 | I37: ='Balance Sheet'!H8 -> 130354 | J37: ='Balance Sheet'!I8 -> 114672.77 | K37: ='Balance Sheet'!J8 -> 87298.701 | L37: ='Balance Sheet'!K8 -> 108755.16 | M37: ='Balance Sheet'!L8 -> 185604.63
A38: Effect of Exchange Rate Changes | C38: 126 | D38: -3950 | E38: -3750 | F38: 3078 | G38: -6510 | H38: 5598 | I38: 0 | J38: 0 | K38: 0 | L38: 0 | M38: 0
A39: Ending Cash Balance | C39: =SUM(C36:C38) -> 139273 | D39: =SUM(D36:D38) -> 216925 | E39: =SUM(E36:E38) -> 194885 | F39: =SUM(F36:F38) -> 153097 | G39: =SUM(G36:G38) -> 183678 | H39: =SUM(H36:H38) -> 133911 | I39: ='Balance Sheet'!I8 -> 114672.77 | J39: ='Balance Sheet'!J8 -> 87298.701 | K39: ='Balance Sheet'!K8 -> 108755.16 | L39: ='Balance Sheet'!L8 -> 185604.63 | M39: ='Balance Sheet'!M8 -> 330724.03
A40: Note: Projected ending cash = Beginning cash + Net change (CFO+CFI+CFF) + FX. Balance Sheet cash linked to this figure. Source: Crocs 10-K FY2025; Model assumptions
A41: Source: Crocs, Inc. Form 10-K FY2020–FY2025 (SEC EDGAR); PitchBook Financial Data (accessed Mar 26–27, 2026); Crocs 8-K Feb 2026 (Q4/FY2025 earnings release)

Sheet NWC
A1: Crocs, Inc. (CROX)
A2: Net Working Capital Projections ($ in thousands)
A4: Fiscal Year | C4: Historical Period | I4: Projection Period
C5: 2020 | D5: 2021 | E5: 2022 | F5: 2023 | G5: 2024 | H5: 2025 | I5: 2026E | J5: 2027E | K5: 2028E | L5: 2029E | M5: 2030E
A6: Revenue | C6: ='Income Statement'!C6 -> 1385951 | D6: ='Income Statement'!D6 -> 2313416 | E6: ='Income Statement'!E6 -> 3554985 | F6: ='Income Statement'!F6 -> 3962347 | G6: ='Income Statement'!G6 -> 4102108 | H6: ='Income Statement'!H6 -> 4040647 | I6: ='Income Statement'!I6 -> 4000240.5 | J6: ='Income Statement'!J6 -> 4040242.9 | ... M6: ='Income Statement'!M6 -> 4470499
A7: COGS | C7: ='Income Statement'!C9 -> 636003 | D7: ='Income Statement'!D9 -> 893196 | E7: ='Income Statement'!E9 -> 1694703 | F7: ='Income Statement'!F9 -> 1752337 | G7: ='Income Statement'!G9 -> 1691850 | H7: ='Income Statement'!H9 -> 1683592 | I7: ='Income Statement'!I9 -> 1660099.8 | J7: ='Income Statement'!J9 -> 1668620.3 | ... M7: ='Income Statement'!M9 -> 1810552.1
A9: Current Assets
A10: Accounts Receivable | C10: ='Balance Sheet'!C9 -> 162520 | D10: ='Balance Sheet'!D9 -> 217182 | E10: ='Balance Sheet'!E9 -> 329188 | F10: ='Balance Sheet'!F9 -> 331231 | G10: ='Balance Sheet'!G9 -> 283907 | H10: ='Balance Sheet'!H9 -> 333055 | I10: ='Balance Sheet'!I9 -> 317827.33 | J10: ='Balance Sheet'!J9 -> 321005.6 | ... M10: ='Balance Sheet'!M9 -> 355190.33
A11: Inventories | C11: ='Balance Sheet'!C10 -> 175121 | D11: ='Balance Sheet'!D10 -> 213520 | E11: ='Balance Sheet'!E10 -> 471551 | F11: ='Balance Sheet'!F10 -> 385054 | G11: ='Balance Sheet'!G10 -> 356254 | H11: ='Balance Sheet'!H10 -> 368687 | I11: ='Balance Sheet'!I10 -> 359309.28 | J11: ='Balance Sheet'!J10 -> 361153.44 | ... M11: ='Balance Sheet'!M10 -> 391872.92
A12: Prepaid Expenses & Other | C12: ='Balance Sheet'!C11 -> 19398 | D12: ='Balance Sheet'!D11 -> 22670 | E12: ='Balance Sheet'!E11 -> 33607 | F12: ='Balance Sheet'!F11 -> 45131 | G12: ='Balance Sheet'!G11 -> 51623 | H12: ='Balance Sheet'!H11 -> 53787 | I12: ='Balance Sheet'!I11 -> 48002.886 | J12: ='Balance Sheet'!J11 -> 48482.915 | ... M12: ='Balance Sheet'!M11 -> 53645.988
A13: Total Current Assets | C13: =SUM(C10:C12) -> 357039 | D13: =SUM(D10:D12) -> 453372 | E13: =SUM(E10:E12) -> 834346 | F13: =SUM(F10:F12) -> 761416 | G13: =SUM(G10:G12) -> 691784 | H13: =SUM(H10:H12) -> 755529 | I13: =SUM(I10:I12) -> 725139.49 | J13: =SUM(J10:J12) -> 730641.96 | ... M13: =SUM(M10:M12) -> 800709.24
A15: Current Liabilities
A16: Accounts Payable | C16: ='Balance Sheet'!C24 -> 136550 | D16: ='Balance Sheet'!D24 -> 198898 | E16: ='Balance Sheet'!E24 -> 357809 | F16: ='Balance Sheet'!F24 -> 350698 | G16: ='Balance Sheet'!G24 -> 390919 | H16: ='Balance Sheet'!H24 -> 336466 | I16: ='Balance Sheet'!I24 -> 350212.84 | J16: ='Balance Sheet'!J24 -> 352010.32 | ... M16: ='Balance Sheet'!M24 -> 381952.09
A17: Accrued Liabilities | C17: ='Balance Sheet'!C25 -> 40164 | D17: ='Balance Sheet'!D25 -> 57057 | E17: ='Balance Sheet'!E25 -> 98571 | F17: ='Balance Sheet'!F25 -> 103255 | G17: ='Balance Sheet'!G25 -> 103435 | H17: ='Balance Sheet'!H25 -> 93051 | I17: ='Balance Sheet'!I25 -> 100006.01 | J17: ='Balance Sheet'!J25 -> 101006.07 | ... M17: ='Balance Sheet'!M25 -> 111762.48
A18: Other Current Liabilities | C18: ='Balance Sheet'!C28 -> 18936 | D18: ='Balance Sheet'!D28 -> 26411 | E18: ='Balance Sheet'!E28 -> 47602 | F18: ='Balance Sheet'!F28 -> 88503 | G18: ='Balance Sheet'!G28 -> 96038 | H18: ='Balance Sheet'!H28 -> 96598 | I18: ='Balance Sheet'!I28 -> 92005.532 | J18: ='Balance Sheet'!J28 -> 92925.588 | ... M18: ='Balance Sheet'!M28 -> 102821.48
A19: Total Current Liabilities | C19: =SUM(C16:C18) -> 195650 | D19: =SUM(D16:D18) -> 282366 | E19: =SUM(E16:E18) -> 503982 | F19: =SUM(F16:F18) -> 542456 | G19: =SUM(G16:G18) -> 590392 | H19: =SUM(H16:H18) -> 526115 | I19: =SUM(I16:I18) -> 542224.38 | J19: =SUM(J16:J18) -> 545941.98 | ... M19: =SUM(M16:M18) -> 596536.04
A21: Net Working Capital (NWC) | C21: =C13-C19 -> 161389 | D21: =D13-D19 -> 171006 | E21: =E13-E19 -> 330364 | F21: =F13-F19 -> 218960 | G21: =G13-G19 -> 101392 | H21: =H13-H19 -> 229414 | I21: =I13-I19 -> 182915.11 | J21: =J13-J19 -> 184699.98 | ... M21: =M13-M19 -> 204173.2
A22: NWC % of Revenue | C22: =(C13-C19)/C6 -> 0.1164464 | D22: =(D13-D19)/D6 -> 0.073919261 | E22: =(E13-E19)/E6 -> 0.092929787 | F22: =(F13-F19)/F6 -> 0.055260178 | G22: =(G13-G19)/G6 -> 0.024717048 | H22: =(H13-H19)/H6 -> 0.056776551 | I22: =(I13-I19)/I6 -> 0.045726027 | J22: =(J13-J19)/J6 -> 0.045715068 | ... M22: =(M13-M19)/M6 -> 0.045671233
A24: Change in NWC (Increase = Use of Cash) | D24: =D21-C21 -> 9617 | E24: =E21-D21 -> 159358 | F24: =F21-E21 -> -111404 | G24: =G21-F21 -> -117568 | H24: =H21-G21 -> 128022 | I24: =I21-H21 -> -46498.892 | J24: =J21-I21 -> 1784.8744 | K24: =K21-J21 -> 4549.4242 | ... M24: =M21-L21 -> 8347.0374
A26: NWC Assumptions
A27: Days Sales Outstanding (DSO) | C27: =(C10/C6)*365 -> 42.800792 | D27: =(D10/D6)*365 -> 34.265964 | E27: =(E10/E6)*365 -> 33.798629 | F27: =(F10/F6)*365 -> 30.512046 | G27: =(G10/G6)*365 -> 25.261659 | H27: =(H10/H6)*365 -> 30.085547 | I27: ='Assumption 2'!D6 -> 29 | J27: ='Assumption 2'!E6 -> 29 | K27: ='Assumption 2'!F6 -> 29 | L27: ='Assumption 2'!G6 -> 29 | M27: ='Assumption 2'!H6 -> 29
A28: Days Inventory Held (DIH) | C28: =(C11/C7)*365 -> 100.50136 | D28: =(D11/D7)*365 -> 87.253861 | E28: =(E11/E7)*365 -> 101.56123 | F28: =(F11/F7)*365 -> 80.204156 | G28: =(G11/G7)*365 -> 76.858297 | H28: =(H11/H7)*365 -> 79.93074 | I28: ='Assumption 2'!D11 -> 79 | J28: ='Assumption 2'!E11 -> 79 | K28: ='Assumption 2'!F11 -> 79 | L28: ='Assumption 2'!G11 -> 79 | M28: ='Assumption 2'!H11 -> 79
A29: Days Payable Outstanding (DPO) | C29: =(C16/C7)*365 -> 78.365589 | D29: =(D16/D7)*365 -> 81.278656 | E29: =(E16/E7)*365 -> 77.063819 | F29: =(F16/F7)*365 -> 73.048032 | G29: =(G16/G7)*365 -> 84.33693 | H29: =(H16/H7)*365 -> 72.94528 | I29: ='Assumption 2'!D16 -> 77 | J29: ='Assumption 2'!E16 -> 77 | K29: ='Assumption 2'!F16 -> 77 | L29: ='Assumption 2'!G16 -> 77 | M29: ='Assumption 2'!H16 -> 77
A30: Prepaid & Other % of Revenue | C30: =C12/C6 -> 0.013996166 | D30: =D12/D6 -> 0.0097993616 | E30: =E12/E6 -> 0.0094534857 | F30: =F12/F6 -> 0.011389967 | G30: =G12/G6 -> 0.012584505 | H30: =H12/H6 -> 0.013311482 | I30: =I12/I6 -> 0.012 | J30: =J12/J6 -> 0.012 | ... M30: =M12/M6 -> 0.012
A31: Accrued Liabilities % of Revenue | C31: =C17/C6 -> 0.02897938 | D31: =D17/D6 -> 0.024663528 | E31: =E17/E6 -> 0.027727543 | F31: =F17/F6 -> 0.02605905 | G31: =G17/G6 -> 0.025215085 | H31: =H17/H6 -> 0.023028738 | I31: =I17/I6 -> 0.025 | J31: =J17/J6 -> 0.025 | ... M31: =M17/M6 -> 0.025
A32: Other CL % of Revenue | C32: =C18/C6 -> 0.013662821 | D32: =D18/D6 -> 0.011416451 | E32: =E18/E6 -> 0.013390211 | F32: =F18/F6 -> 0.022336004 | G32: =G18/G6 -> 0.023411865 | H32: =H18/H6 -> 0.023906567 | I32: =I18/I6 -> 0.023 | J32: =J18/J6 -> 0.023 | ... M32: =M18/M6 -> 0.023

Sheet WACC
A1: Crocs, Inc. (CROX)
A2: Weighted Average Cost of Capital (WACC) – ($ in thousands)
A4: Capital Structure
A5: Debt-to-Total Capitalization | C5: =1613849/5613849 -> 0.28747638
A6: Equity-to-Total Capitalization | C6: =4000000/5613849 -> 0.71252362
A8: Cost of Debt
A9: Pre-Tax Cost of Debt | C9: =88287/1613849 -> 0.054705862 | Q9: =C26 / (1 + (1 - G26) * F26) -> 1.536403
A10: Effective Tax Rate | C10: 0.215
A11: After-Tax Cost of Debt | C11: =C9*(1-C10) -> 0.042944101
A13: Cost of Equity (CAPM)
A14: Risk-Free Rate (10-yr Treasury) | C14: 0.0444
A15: Equity Risk Premium (ERP) | C15: 0.0446
A16: Unlevered Beta (from comps) | C16: =H33 -> 1.4496032
A17: Relevered Beta | C17: =C16*(1+(1-C10)*C5/C6) -> 1.9087184
A18: Size Premium | C18: 0.028016 | D18: Duff & Phelps size premium for ~$4B market cap (8th-9th decile): 2.0-3.5% range. Using 2.80% reflecting CROX single-brand concentration risk, HEYDUDE turnaround uncertainty, and elevated execution risk vs. diversified footwear peers. Source: Duff & Phelps 2024 SBBI.
A19: Cost of Equity | C19: =C14+C17*C15+C18 -> 0.15754484
A21: WACC Calculation
A22: WACC | C22: =C6*C19+C5*C11 -> 0.12459983
A24: Comparable Companies – Beta Unlevering
A25: Company | B25: Ticker | C25: Levered Beta | D25: Market Value Equity ($M) | E25: Total Debt ($M) | F25: D/E Ratio | G25: Tax Rate | H25: Unlevered Beta
A26: Steve Madden | C26: 1.78 | D26: ='Comparable Companies '!C5 -> 2410 | E26: 486.14 | F26: =E26/D26 -> 0.20171784 | G26: 0.214 | H26: =C26 / (1 + (1 - G26) * F26) -> 1.536403
A27: Wolverine World Wide | C27: 2.71 | D27: ='Comparable Companies '!C6 -> 1290 | E27: 762 | F27: =E27/D27 -> 0.59069767 | G27: 0.109 | H27: =C27 / (1 + (1 - G27) * F27) -> 1.7755221
A28: Columbia Sportswear | C28: 0.78 | D28: ='Comparable Companies '!C7 -> 2860 | E28: 477.69 | F28: =E28/D28 -> 0.16702448 | G28: 0.228 | H28: =C28 / (1 + (1 - G28) * F28) -> 0.69091183
A29: Deckers Outdoor | C29: 1.39 | D29: ='Comparable Companies '!C8 -> 13350 | E29: 342.88 | F29: =E29/D29 -> 0.025683895 | G29: 0.223 | H29: =C29 / (1 + (1 - G29) * F29) -> 1.3628034
A30: On Holding | C30: 2.45 | D30: ='Comparable Companies '!C9 -> 10720 | E30: 658.53 | F30: =E30/D30 -> 0.061430037 | G30: 0.196 | H30: =C30 / (1 + (1 - G30) * F30) -> 2.3346902
A31: Birkenstock | C31: 1.06 | D31: ='Comparable Companies '!C10 -> 6290 | E31: 1536.07 | F31: =E31/D31 -> 0.24420827 | G31: 0.242 | H31: =C31 / (1 + (1 - G31) * F31) -> 0.89443184
A32: Mean | C32: =AVERAGE(C26:C31) -> 1.695 | D32: =AVERAGE(D26:D31) -> 6153.3333 | E32: =AVERAGE(E26:E31) -> 710.55167 | F32: =AVERAGE(F26:F31) -> 0.21512703 | G32: =AVERAGE(G26:G31) -> 0.202 | H32: =AVERAGE(H26:H31) -> 1.4324604
A33: Median | C33: =MEDIAN(C26:C31) -> 1.585 | D33: =MEDIAN(D26:D31) -> 4575 | E33: =MEDIAN(E26:E31) -> 572.335 | F33: =MEDIAN(F26:F31) -> 0.18437116 | G33: =MEDIAN(G26:G31) -> 0.2185 | H33: =MEDIAN(H26:H31) -> 1.4496032
A35: WACC Sensitivity (Pre-Tax Cost of Debt vs. Debt/Total Cap.)
A36: D/TC \ CoD → | B36: 0.03 | C36: 0.035 | D36: 0.04 | E36: 0.045 | F36: 0.05
A37: 0.15 | B37: =(1-0.15)*$C$19+0.15*B36*(1-$C$10) -> 0.13744561 | C37: =(1-0.15)*$C$19+0.15*C36*(1-$C$10) -> 0.13803436 | D37: =(1-0.15)*$C$19+0.15*D36*(1-$C$10) -> 0.13862311 | E37: =(1-0.15)*$C$19+0.15*E36*(1-$C$10) -> 0.13921186 | F37: =(1-0.15)*$C$19+0.15*F36*(1-$C$10) -> 0.13980061
A38: 0.2 | B38: =(1-0.2)*$C$19+0.2*B36*(1-$C$10) -> 0.13074587 | C38: =(1-0.2)*$C$19+0.2*C36*(1-$C$10) -> 0.13153087 | D38: =(1-0.2)*$C$19+0.2*D36*(1-$C$10) -> 0.13231587 | E38: =(1-0.2)*$C$19+0.2*E36*(1-$C$10) -> 0.13310087 | F38: =(1-0.2)*$C$19+0.2*F36*(1-$C$10) -> 0.13388587
A39: 0.25 | B39: =(1-0.25)*$C$19+0.25*B36*(1-$C$10) -> 0.12404613 | C39: =(1-0.25)*$C$19+0.25*C36*(1-$C$10) -> 0.12502738 | D39: =(1-0.25)*$C$19+0.25*D36*(1-$C$10) -> 0.12600863 | E39: =(1-0.25)*$C$19+0.25*E36*(1-$C$10) -> 0.12698988 | F39: =(1-0.25)*$C$19+0.25*F36*(1-$C$10) -> 0.12797113
A40: 0.3 | B40: =(1-0.3)*$C$19+0.3*B36*(1-$C$10) -> 0.11734639 | C40: =(1-0.3)*$C$19+0.3*C36*(1-$C$10) -> 0.11852389 | D40: =(1-0.3)*$C$19+0.3*D36*(1-$C$10) -> 0.11970139 | E40: =(1-0.3)*$C$19+0.3*E36*(1-$C$10) -> 0.12087889 | F40: =(1-0.3)*$C$19+0.3*F36*(1-$C$10) -> 0.12205639
A41: 0.35 | B41: =(1-0.35)*$C$19+0.35*B36*(1-$C$10) -> 0.11064665 | C41: =(1-0.35)*$C$19+0.35*C36*(1-$C$10) -> 0.1120204 | D41: =(1-0.35)*$C$19+0.35*D36*(1-$C$10) -> 0.11339415 | E41: =(1-0.35)*$C$19+0.35*E36*(1-$C$10) -> 0.1147679 | F41: =(1-0.35)*$C$19+0.35*F36*(1-$C$10) -> 0.11614165
A42: 0.4 | B42: =(1-0.4)*$C$19+0.4*B36*(1-$C$10) -> 0.1039469 | C42: =(1-0.4)*$C$19+0.4*C36*(1-$C$10) -> 0.1055169 | D42: =(1-0.4)*$C$19+0.4*D36*(1-$C$10) -> 0.1070869 | E42: =(1-0.4)*$C$19+0.4*E36*(1-$C$10) -> 0.1086569 | F42: =(1-0.4)*$C$19+0.4*F36*(1-$C$10) -> 0.1102269
A43: Note: Yellow = base case approx. (D/TC≈30%, Pre-Tax CoD≈5%). Cost of Equity fixed at CAPM rate (C19). Source: WACC inputs; Damodaran ERP Jan 2026; US Treasury 10-yr Mar 27 2026; Hamada beta unlevering.

Sheet DCF
A1: Crocs, Inc. (CROX)
A2: Discounted Cash Flow Analysis ($ in thousands, fiscal year ending December 31)
A3: Operating Scenario | C3: 1 = Base | 2 = Upside | 3 = Downside
A4: Mid-Year Convention | C4: 1
A5: Fiscal Year | C5: Historical Period | I5: Projection Period
C6: 2020 | D6: 2021 | E6: 2022 | F6: 2023 | G6: 2024 | H6: 2025 | I6: 2026E | J6: 2027E | K6: 2028E | L6: 2029E | M6: 2030E
A7: Revenue | C7: ='Income Statement'!C6 -> 1385951 | D7: ='Income Statement'!D6 -> 2313416 | E7: ='Income Statement'!E6 -> 3554985 | F7: ='Income Statement'!F6 -> 3962347 | G7: ='Income Statement'!G6 -> 4102108 | H7: ='Income Statement'!H6 -> 4040647 | I7: ='Income Statement'!I6 -> 4000240.5 | J7: ='Income Statement'!J6 -> 4040242.9 | ... M7: ='Income Statement'!M6 -> 4470499
A8: % Growth | D8: =(D7/C7)-1 -> 0.66919032 | E8: =(E7/D7)-1 -> 0.53668212 | F8: =(F7/E7)-1 -> 0.11458895 | G8: =(G7/F7)-1 -> 0.035272277 | H8: =(H7/G7)-1 -> -0.014982784 | I8: =(I7/H7)-1 -> -0.01 | J8: =(J7/I7)-1 -> 0.01 | K8: =(K7/J7)-1 -> 0.025 | ... M8: =(M7/L7)-1 -> 0.043
A10: Cost of Goods Sold | C10: ='Income Statement'!C9 -> 636003 | D10: ='Income Statement'!D9 -> 893196 | E10: ='Income Statement'!E9 -> 1694703 | F10: ='Income Statement'!F9 -> 1752337 | G10: ='Income Statement'!G9 -> 1691850 | H10: ='Income Statement'!H9 -> 1683592 | I10: ='Income Statement'!I9 -> 1660099.8 | J10: ='Income Statement'!J9 -> 1668620.3 | ... M10: ='Income Statement'!M9 -> 1810552.1
A12: Gross Profit | C12: =C7-C10 -> 749948 | D12: =D7-D10 -> 1420220 | E12: =E7-E10 -> 1860282 | F12: =F7-F10 -> 2210010 | G12: =G7-G10 -> 2410258 | H12: =H7-H10 -> 2357055 | I12: =I7-I10 -> 2340140.7 | J12: =J7-J10 -> 2371622.6 | ... M12: =M7-M10 -> 2659946.9
A13: Gross Margin %
A15: SG&A | C15: ='Income Statement'!C15 -> 514753 | D15: ='Income Statement'!D15 -> 737156 | E15: ='Income Statement'!E15 -> 982706 | F15: ='Income Statement'!F15 -> 1151064 | G15: ='Income Statement'!G15 -> 1338032 | H15: ='Income Statement'!H15 -> 1435580 | I15: ='Income Statement'!I15 -> 1400084.2 | J15: ='Income Statement'!J15 -> 1393883.8 | ... M15: ='Income Statement'!M15 -> 1475264.7
A16: Depreciation & Amortization | C16: ='Income Statement'!C17 -> 0 | D16: ='Income Statement'!D17 -> 0 | E16: ='Income Statement'!E17 -> 26820 | F16: ='Income Statement'!F17 -> 12876 | G16: ='Income Statement'!G17 -> 26233 | H16: ='Income Statement'!H17 -> 33845 | I16: ='Income Statement'!I17 -> 80004.811 | J16: ='Income Statement'!J17 -> 80804.859 | ... M16: ='Income Statement'!M17 -> 89409.98
A18: EBIT | C18: ='Income Statement'!C20 -> 235195 | D18: ='Income Statement'!D20 -> 683064 | E18: ='Income Statement'!E20 -> 850756 | F18: ='Income Statement'!F20 -> 1046070 | G18: ='Income Statement'!G20 -> 1045993 | H18: ='Income Statement'!H20 -> 887630 | I18: ='Income Statement'!I20 -> 860051.71 | J18: ='Income Statement'!J20 -> 896933.93 | ... M18: ='Income Statement'!M20 -> 1095272.3
A19: EBIT Margin % | C19: =C18/C7 -> 0.16969936 | D19: =D18/D7 -> 0.29526207 | E19: =E18/E7 -> 0.23931353 | F19: =F18/F7 -> 0.26400262 | G19: =G18/G7 -> 0.25498914 | H19: =H18/H7 -> 0.21967522 | I19: =I18/I7 -> 0.215 | J19: =J18/J7 -> 0.222 | ... M19: =M18/M7 -> 0.245
A21: Taxes (@ Effective Rate) | C21: =C18*WACC!$C$10 -> 50566.925 | D21: =D18*WACC!$C$10 -> 146858.76 | E21: =E18*WACC!$C$10 -> 182912.54 | F21: =F18*WACC!$C$10 -> 224905.05 | G21: =G18*WACC!$C$10 -> 224888.49 | H21: =H18*WACC!$C$10 -> 190840.45 | I21: =I18*WACC!$C$10 -> 184911.12 | J21: =J18*WACC!$C$10 -> 192840.8 | ... M21: =M18*WACC!$C$10 -> 235483.54
A23: EBIAT (NOPAT) | C23: =C18-C21 -> 184628.08 | D23: =D18-D21 -> 536205.24 | E23: =E18-E21 -> 667843.46 | F23: =F18-F21 -> 821164.95 | G23: =G18-G21 -> 821104.51 | H23: =H18-H21 -> 696789.55 | I23: =I18-I21 -> 675140.6 | J23: =J18-J21 -> 704093.14 | ... M23: =M18-M21 -> 859788.72
A25: Plus: Depreciation & Amortization | C25: ='Cash Flow Statement'!C8 -> 27619 | D25: ='Cash Flow Statement'!D8 -> 31976 | E25: ='Cash Flow Statement'!E8 -> 39229 | F25: ='Cash Flow Statement'!F8 -> 54304 | G25: ='Cash Flow Statement'!G8 -> 69840 | H25: ='Cash Flow Statement'!H8 -> 79282 | I25: ='Cash Flow Statement'!I8 -> 80004.811 | J25: ='Cash Flow Statement'!J8 -> 80804.859 | ... M25: ='Cash Flow Statement'!M8 -> 89409.98
A26: Less: Capital Expenditures | C26: ='Cash Flow Statement'!C22 -> -42033 | D26: ='Cash Flow Statement'!D22 -> -55916 | E26: ='Cash Flow Statement'!E22 -> -104190 | F26: ='Cash Flow Statement'!F22 -> -115625 | G26: ='Cash Flow Statement'!G22 -> -69347 | H26: ='Cash Flow Statement'!H22 -> -51231 | I26: ='Cash Flow Statement'!I22 -> -72004.33 | J26: ='Cash Flow Statement'!J22 -> -72724.373 | ... M26: ='Cash Flow Statement'!M22 -> -80468.982
A27: Less: Inc./(Dec.) in Net Working Capital | C27: =NWC!C24 -> 0 | D27: =NWC!D24 -> 9617 | E27: =NWC!E24 -> 159358 | F27: =NWC!F24 -> -111404 | G27: =NWC!G24 -> -117568 | H27: =NWC!H24 -> 128022 | I27: =NWC!I24 -> -46498.892 | J27: =NWC!J24 -> 1784.8744 | ... M27: =NWC!M24 -> 8347.0374
A29: Unlevered Free Cash Flow | C29: =C23+C25+C26-C27 -> 170214.08 | D29: =D23+D25+D26-D27 -> 502648.24 | E29: =E23+E25+E26-E27 -> 443524.46 | F29: =F23+F25+F26-F27 -> 871247.95 | G29: =G23+G25+G26-G27 -> 939165.51 | H29: =H23+H25+H26-H27 -> 596818.55 | I29: =I23+I25+I26-I27 -> 729639.97 | J29: =J23+J25+J26-J27 -> 710388.75 | ... M29: =M23+M25+M26-M27 -> 860382.68
A31: WACC | I31: =WACC!$C$22 -> 0.12459983 | J31: =WACC!$C$22 -> 0.12459983 | K31: =WACC!$C$22 -> 0.12459983 | L31: =WACC!$C$22 -> 0.12459983 | M31: =WACC!$C$22 -> 0.12459983
A32: Discount Period | I32: 0.5 | J32: 1.5 | K32: 2.5 | L32: 3.5 | M32: 4.5
A33: Discount Factor | I33: =1/(1+I31)^I32 -> 0.94297677 | J33: =1/(1+J31)^J32 -> 0.83849983 | K33: =1/(1+K31)^K32 -> 0.74559839 | L33: =1/(1+L31)^L32 -> 0.66298995 | M33: =1/(1+M31)^M32 -> 0.5895341
A35: PV of Free Cash Flow | I35: =I29*I33 -> 688033.54 | J35: =J29*J33 -> 595660.84 | K35: =K29*K33 -> 560269.16 | L35: =L29*L33 -> 530007.66 | M35: =M29*M33 -> 507224.93
A37: Terminal Value & Enterprise Value Bridge
A38: Sum of PV of FCFs | C38: =SUM(I35:M35) -> 2881196.1
A39: Terminal Growth Rate | C39: 0.02
A40: Terminal Year FCF | C40: =M29 -> 860382.68
A41: Terminal Value (Gordon Growth) | C41: =C40*(1+C39)/(WACC!$C$22-C39) -> 8389978.3
A42: PV of Terminal Value | C42: =C41*M33 -> 4946178.3
A43: Enterprise Value (EV) | C43: =C38+C42 -> 7827374.4
A44: (+) Cash & Cash Equivalents | C44: ='Balance Sheet'!H8 -> 130354
A45: (-) Total Debt | C45: =('Balance Sheet'!H27+'Balance Sheet'!H32) -> 1613849
A46: (-) Minority Interest | C46: 0
A47: Equity Value | C47: =C43+C44-C45-C46 -> 6343879.4
A48: Diluted Shares Outstanding (000s) | C48: 54208
A49: Implied Share Price | C49: =C47/C48 -> 117.02847
A50: Current Share Price | C50: 79.54
A51: Implied Upside / (Downside) | C51: =(C49-C50)/C50 -> 0.47131597
A53: Sensitivity Analysis – Implied Share Price (WACC vs. Terminal Growth Rate)
A54: TGR / WACC → | C54: 0.09 | D54: 0.1 | E54: 0.11 | F54: 0.12 | G54: 0.1246 | H54: 0.13 | I54: 0.14 | J54: 10.5%
A55: 0.01 | C55: =IFERROR(((I29/(1+C54)^0.5+J29/(1+C54)^1.5+K29/(1+C54)^2.5+L29/(1+C54)^3.5+M29/(1+C54)^4.5)+(M29*(1+A55)/(C54-A55)/(1+C54)^4.5)+'Balance Sheet'!H8-('Balance Sheet'!H27+'Balance Sheet'!H32))/54208,"N/A") -> 165.86312 | D55: =IFERROR(((I29/(1+D54)^0.5+J29/(1+D54)^1.5+K29/(1+D54)^2.5+L29/(1+D54)^3.5+M29/(1+D54)^4.5)+(M29*(1+A55)/(D54-A55)/(1+D54)^4.5)+'Balance Sheet'!H8-('Balance Sheet'!H27+'Balance Sheet'!H32))/54208,"N/A") -> 144.64474 | E55: =IFERROR(((I29/(1+E54)^0.5+J29/(1+E54)^1.5+K29/(1+E54)^2.5+L29/(1+E54)^3.5+M29/(1+E54)^4.5)+(M29*(1+A55)/(E54-A55)/(1+E54)^4.5)+'Balance Sheet'!H8-('Balance Sheet'!H27+'Balance Sheet'!H32))/54208,"N/A") -> 127.68189 | F55: =IFERROR(((I29/(1+F54)^0.5+J29/(1+F54)^1.5+K29/(1+F54)^2.5+L29/(1+F54)^3.5+M29/(1+F54)^4.5)+(M29*(1+A55)/(F54-A55)/(1+F54)^4.5)+'Balance Sheet'!H8-('Balance Sheet'!H27+'Balance Sheet'!H32))/54208,"N/A") -> 113.81339 | G55: =IFERROR(((I29/(1+G54)^0.5+J29/(1+G54)^1.5+K29/(1+G54)^2.5+L29/(1+G54)^3.5+M29/(1+G54)^4.5)+(M29*(1+A55)/(G54-A55)/(1+G54)^4.5)+'Balance Sheet'!H8-('Balance Sheet'!H27+'Balance Sheet'!H32))/54208,"N/A") -> 108.24978 | H55: =IFERROR(((I29/(1+H54)^0.5+J29/(1+H54)^1.5+K29/(1+H54)^2.5+L29/(1+H54)^3.5+M29/(1+H54)^4.5)+(M29*(1+A55)/(H54-A55)/(1+H54)^4.5)+'Balance Sheet'!H8-('Balance Sheet'!H27+'Balance Sheet'!H32))/54208,"N/A") -> 102.26518 | I55: =IFERROR(((I29/(1+I54)^0.5+J29/(1+I54)^1.5+K29/(1+I54)^2.5+L29/(1+I54)^3.5+M29/(1+I54)^4.5)+(M29*(1+A55)/(I54-A55)/(1+I54)^4.5)+'Balance Sheet'!H8-('Balance Sheet'!H27+'Balance Sheet'!H32))/54208,"N/A") -> 92.50138
A56: 0.015 | C56: =IFERROR(((I29/(1+C54)^0.5+J29/(1+C54)^1.5+K29/(1+C54)^2.5+L29/(1+C54)^3.5+M29/(1+C54)^4.5)+(M29*(1+A56)/(C54-A56)/(1+C54)^4.5)+'Balance Sheet'!H8-('Balance Sheet'!H27+'Balance Sheet'!H32))/54208,"N/A") -> 175.64572 | D56: =IFERROR(((I29/(1+D54)^0.5+J29/(1+D54)^1.5+K29/(1+D54)^2.5+L29/(1+D54)^3.5+M29/(1+D54)^4.5)+(M29*(1+A56)/(D54-A56)/(1+D54)^4.5)+'Balance Sheet'!H8-('Balance Sheet'!H27+'Balance Sheet'!H32))/54208,"N/A") -> 152.076 | E56: =IFERROR(((I29/(1+E54)^0.5+J29/(1+E54)^1.5+K29/(1+E54)^2.5+L29/(1+E54)^3.5+M29/(1+E54)^4.5)+(M29*(1+A56)/(E54-A56)/(1+E54)^4.5)+'Balance Sheet'!H8-('Balance Sheet'!H27+'Balance Sheet'!H32))/54208,"N/A") -> 133.47944 | F56: =IFERROR(((I29/(1+F54)^0.5+J29/(1+F54)^1.5+K29/(1+F54)^2.5+L29/(1+F54)^3.5+M29/(1+F54)^4.5)+(M29*(1+A56)/(F54-A56)/(1+F54)^4.5)+'Balance Sheet'!H8-('Balance Sheet'!H27+'Balance Sheet'!H32))/54208,"N/A") -> 118.43458 | G56: =IFERROR(((I29/(1+G54)^0.5+J29/(1+G54)^1.5+K29/(1+G54)^2.5+L29/(1+G54)^3.5+M29/(1+G54)^4.5)+(M29*(1+A56)/(G54-A56)/(1+G54)^4.5)+'Balance Sheet'!H8-('Balance Sheet'!H27+'Balance Sheet'!H32))/54208,"N/A") -> 112.43878 | H56: =IFERROR(((I29/(1+H54)^0.5+J29/(1+H54)^1.5+K29/(1+H54)^2.5+L29/(1+H54)^3.5+M29/(1+H54)^4.5)+(M29*(1+A56)/(H54-A56)/(1+H54)^4.5)+'Balance Sheet'!H8-('Balance Sheet'!H27+'Balance Sheet'!H32))/54208,"N/A") -> 106.01443 | I56: =IFERROR(((I29/(1+I54)^0.5+J29/(1+I54)^1.5+K29/(1+I54)^2.5+L29/(1+I54)^3.5+M29/(1+I54)^4.5)+(M29*(1+A56)/(I54-A56)/(1+I54)^4.5)+'Balance Sheet'!H8-('Balance Sheet'!H27+'Balance Sheet'!H32))/54208,"N/A") -> 95.588673
A57: 0.02 | C57: =IFERROR(((I29/(1+C54)^0.5+J29/(1+C54)^1.5+K29/(1+C54)^2.5+L29/(1+C54)^3.5+M29/(1+C54)^4.5)+(M29*(1+A57)/(C54-A57)/(1+C54)^4.5)+'Balance Sheet'!H8-('Balance Sheet'!H27+'Balance Sheet'!H32))/54208,"N/A") -> 186.82583 | D57: =IFERROR(((I29/(1+D54)^0.5+J29/(1+D54)^1.5+K29/(1+D54)^2.5+L29/(1+D54)^3.5+M29/(1+D54)^4.5)+(M29*(1+A57)/(D54-A57)/(1+D54)^4.5)+'Balance Sheet'!H8-('Balance Sheet'!H27+'Balance Sheet'!H32))/54208,"N/A") -> 160.43617 | E57: =IFERROR(((I29/(1+E54)^0.5+J29/(1+E54)^1.5+K29/(1+E54)^2.5+L29/(1+E54)^3.5+M29/(1+E54)^4.5)+(M29*(1+A57)/(E54-A57)/(1+E54)^4.5)+'Balance Sheet'!H8-('Balance Sheet'!H27+'Balance Sheet'!H32))/54208,"N/A") -> 139.92115 | F57: =IFERROR(((I29/(1+F54)^0.5+J29/(1+F54)^1.5+K29/(1+F54)^2.5+L29/(1+F54)^3.5+M29/(1+F54)^4.5)+(M29*(1+A57)/(F54-A57)/(1+F54)^4.5)+'Balance Sheet'!H8-('Balance Sheet'!H27+'Balance Sheet'!H32))/54208,"N/A") -> 123.51788 | G57: =IFERROR(((I29/(1+G54)^0.5+J29/(1+G54)^1.5+K29/(1+G54)^2.5+L29/(1+G54)^3.5+M29/(1+G54)^4.5)+(M29*(1+A57)/(G54-A57)/(1+G54)^4.5)+'Balance Sheet'!H8-('Balance Sheet'!H27+'Balance Sheet'!H32))/54208,"N/A") -> 117.02825 | H57: =IFERROR(((I29/(1+H54)^0.5+J29/(1+H54)^1.5+K29/(1+H54)^2.5+L29/(1+H54)^3.5+M29/(1+H54)^4.5)+(M29*(1+A57)/(H54-A57)/(1+H54)^4.5)+'Balance Sheet'!H8-('Balance Sheet'!H27+'Balance Sheet'!H32))/54208,"N/A") -> 110.10453 | I57: =IFERROR(((I29/(1+I54)^0.5+J29/(1+I54)^1.5+K29/(1+I54)^2.5+L29/(1+I54)^3.5+M29/(1+I54)^4.5)+(M29*(1+A57)/(I54-A57)/(1+I54)^4.5)+'Balance Sheet'!H8-('Balance Sheet'!H27+'Balance Sheet'!H32))/54208,"N/A") -> 98.933241
A58: 0.025 | C58: =IFERROR(((I29/(1+C54)^0.5+J29/(1+C54)^1.5+K29/(1+C54)^2.5+L29/(1+C54)^3.5+M29/(1+C54)^4.5)+(M29*(1+A58)/(C54-A58)/(1+C54)^4.5)+'Balance Sheet'!H8-('Balance Sheet'!H27+'Balance Sheet'!H32))/54208,"N/A") -> 199.72596 | D58: =IFERROR(((I29/(1+D54)^0.5+J29/(1+D54)^1.5+K29/(1+D54)^2.5+L29/(1+D54)^3.5+M29/(1+D54)^4.5)+(M29*(1+A58)/(D54-A58)/(1+D54)^4.5)+'Balance Sheet'!H8-('Balance Sheet'!H27+'Balance Sheet'!H32))/54208,"N/A") -> 169.91103 | E58: =IFERROR(((I29/(1+E54)^0.5+J29/(1+E54)^1.5+K29/(1+E54)^2.5+L29/(1+E54)^3.5+M29/(1+E54)^4.5)+(M29*(1+A58)/(E54-A58)/(1+E54)^4.5)+'Balance Sheet'!H8-('Balance Sheet'!H27+'Balance Sheet'!H32))/54208,"N/A") -> 147.12072 | F58: =IFERROR(((I29/(1+F54)^0.5+J29/(1+F54)^1.5+K29/(1+F54)^2.5+L29/(1+F54)^3.5+M29/(1+F54)^4.5)+(M29*(1+A58)/(F54-A58)/(1+F54)^4.5)+'Balance Sheet'!H8-('Balance Sheet'!H27+'Balance Sheet'!H32))/54208,"N/A") -> 129.13627 | G58: =IFERROR(((I29/(1+G54)^0.5+J29/(1+G54)^1.5+K29/(1+G54)^2.5+L29/(1+G54)^3.5+M29/(1+G54)^4.5)+(M29*(1+A58)/(G54-A58)/(1+G54)^4.5)+'Balance Sheet'!H8-('Balance Sheet'!H27+'Balance Sheet'!H32))/54208,"N/A") -> 122.07851 | H58: =IFERROR(((I29/(1+H54)^0.5+J29/(1+H54)^1.5+K29/(1+H54)^2.5+L29/(1+H54)^3.5+M29/(1+H54)^4.5)+(M29*(1+A58)/(H54-A58)/(1+H54)^4.5)+'Balance Sheet'!H8-('Balance Sheet'!H27+'Balance Sheet'!H32))/54208,"N/A") -> 114.58415 | I58: =IFERROR(((I29/(1+I54)^0.5+J29/(1+I54)^1.5+K29/(1+I54)^2.5+L29/(1+I54)^3.5+M29/(1+I54)^4.5)+(M29*(1+A58)/(I54-A58)/(1+I54)^4.5)+'Balance Sheet'!H8-('Balance Sheet'!H27+'Balance Sheet'!H32))/54208,"N/A") -> 102.56864
A59: 0.03 | C59: =IFERROR(((I29/(1+C54)^0.5+J29/(1+C54)^1.5+K29/(1+C54)^2.5+L29/(1+C54)^3.5+M29/(1+C54)^4.5)+(M29*(1+A59)/(C54-A59)/(1+C54)^4.5)+'Balance Sheet'!H8-('Balance Sheet'!H27+'Balance Sheet'!H32))/54208,"N/A") -> 214.77612 | D59: =IFERROR(((I29/(1+D54)^0.5+J29/(1+D54)^1.5+K29/(1+D54)^2.5+L29/(1+D54)^3.5+M29/(1+D54)^4.5)+(M29*(1+A59)/(D54-A59)/(1+D54)^4.5)+'Balance Sheet'!H8-('Balance Sheet'!H27+'Balance Sheet'!H32))/54208,"N/A") -> 180.73943 | E59: =IFERROR(((I29/(1+E54)^0.5+J29/(1+E54)^1.5+K29/(1+E54)^2.5+L29/(1+E54)^3.5+M29/(1+E54)^4.5)+(M29*(1+A59)/(E54-A59)/(1+E54)^4.5)+'Balance Sheet'!H8-('Balance Sheet'!H27+'Balance Sheet'!H32))/54208,"N/A") -> 155.22024 | F59: =IFERROR(((I29/(1+F54)^0.5+J29/(1+F54)^1.5+K29/(1+F54)^2.5+L29/(1+F54)^3.5+M29/(1+F54)^4.5)+(M29*(1+A59)/(F54-A59)/(1+F54)^4.5)+'Balance Sheet'!H8-('Balance Sheet'!H27+'Balance Sheet'!H32))/54208,"N/A") -> 135.37892 | G59: =IFERROR(((I29/(1+G54)^0.5+J29/(1+G54)^1.5+K29/(1+G54)^2.5+L29/(1+G54)^3.5+M29/(1+G54)^4.5)+(M29*(1+A59)/(G54-A59)/(1+G54)^4.5)+'Balance Sheet'!H8-('Balance Sheet'!H27+'Balance Sheet'!H32))/54208,"N/A") -> 127.66263 | H59: =IFERROR(((I29/(1+H54)^0.5+J29/(1+H54)^1.5+K29/(1+H54)^2.5+L29/(1+H54)^3.5+M29/(1+H54)^4.5)+(M29*(1+A59)/(H54-A59)/(1+H54)^4.5)+'Balance Sheet'!H8-('Balance Sheet'!H27+'Balance Sheet'!H32))/54208,"N/A") -> 119.51174 | I59: =IFERROR(((I29/(1+I54)^0.5+J29/(1+I54)^1.5+K29/(1+I54)^2.5+L29/(1+I54)^3.5+M29/(1+I54)^4.5)+(M29*(1+A59)/(I54-A59)/(1+I54)^4.5)+'Balance Sheet'!H8-('Balance Sheet'!H27+'Balance Sheet'!H32))/54208,"N/A") -> 106.53453
A60: 0.035 | C60: =IFERROR(((I29/(1+C54)^0.5+J29/(1+C54)^1.5+K29/(1+C54)^2.5+L29/(1+C54)^3.5+M29/(1+C54)^4.5)+(M29*(1+A60)/(C54-A60)/(1+C54)^4.5)+'Balance Sheet'!H8-('Balance Sheet'!H27+'Balance Sheet'!H32))/54208,"N/A") -> 232.56266 | D60: =IFERROR(((I29/(1+D54)^0.5+J29/(1+D54)^1.5+K29/(1+D54)^2.5+L29/(1+D54)^3.5+M29/(1+D54)^4.5)+(M29*(1+A60)/(D54-A60)/(1+D54)^4.5)+'Balance Sheet'!H8-('Balance Sheet'!H27+'Balance Sheet'!H32))/54208,"N/A") -> 193.23375 | E60: =IFERROR(((I29/(1+E54)^0.5+J29/(1+E54)^1.5+K29/(1+E54)^2.5+L29/(1+E54)^3.5+M29/(1+E54)^4.5)+(M29*(1+A60)/(E54-A60)/(1+E54)^4.5)+'Balance Sheet'!H8-('Balance Sheet'!H27+'Balance Sheet'!H32))/54208,"N/A") -> 164.39968 | F60: =IFERROR(((I29/(1+F54)^0.5+J29/(1+F54)^1.5+K29/(1+F54)^2.5+L29/(1+F54)^3.5+M29/(1+F54)^4.5)+(M29*(1+A60)/(F54-A60)/(1+F54)^4.5)+'Balance Sheet'!H8-('Balance Sheet'!H27+'Balance Sheet'!H32))/54208,"N/A") -> 142.356 | G60: =IFERROR(((I29/(1+G54)^0.5+J29/(1+G54)^1.5+K29/(1+G54)^2.5+L29/(1+G54)^3.5+M29/(1+G54)^4.5)+(M29*(1+A60)/(G54-A60)/(1+G54)^4.5)+'Balance Sheet'!H8-('Balance Sheet'!H27+'Balance Sheet'!H32))/54208,"N/A") -> 133.86997 | H60: =IFERROR(((I29/(1+H54)^0.5+J29/(1+H54)^1.5+K29/(1+H54)^2.5+L29/(1+H54)^3.5+M29/(1+H54)^4.5)+(M29*(1+A60)/(H54-A60)/(1+H54)^4.5)+'Balance Sheet'!H8-('Balance Sheet'!H27+'Balance Sheet'!H32))/54208,"N/A") -> 124.95802 | I60: =IFERROR(((I29/(1+I54)^0.5+J29/(1+I54)^1.5+K29/(1+I54)^2.5+L29/(1+I54)^3.5+M29/(1+I54)^4.5)+(M29*(1+A60)/(I54-A60)/(1+I54)^4.5)+'Balance Sheet'!H8-('Balance Sheet'!H27+'Balance Sheet'!H32))/54208,"N/A") -> 110.87813

Sheet Valuation Summary
A1: Crocs, Inc. (CROX) – Valuation Summary
A2: ($ in thousands unless noted per share)
A4: DCF Valuation – Base Case
B5: Bear Case | C5: Base Case | D5: Bull Case
A6: PV of Free Cash Flows | C6: =DCF!C38 -> 2881196.1
A7: PV of Terminal Value | C7: =DCF!C42 -> 4946178.3
A8: Enterprise Value (EV) | C8: =DCF!C43 -> 7827374.4
A9: (+) Cash & Cash Equivalents | C9: =DCF!C44 -> 130354
A10: (-) Total Debt | C10: =DCF!C45 -> 1613849
A11: Equity Value | C11: =DCF!C47 -> 6343879.4
A12: ÷ Diluted Shares (000s) | C12: =DCF!C48 -> 54208
A13: Implied Share Price | B13: =IFERROR(DCF!I55,0) -> 92.50138 | C13: =DCF!C49 -> 117.02847 | D13: =IFERROR(DCF!C60,0) -> 232.56266
A14: Current Share Price | C14: =DCF!C50 -> 79.54
A15: Upside / (Downside) | B15: =IFERROR((DCF!I55-DCF!C50)/DCF!C50,"N/A") -> 0.16295423 | C15: =IFERROR(DCF!C51,"N/A") -> 0.47131597 | D15: =IFERROR((DCF!C60-DCF!C50)/DCF!C50,"N/A") -> 1.9238454
A16: Source: DCF model. Bear: WACC=14.0%, TGR=1.0%. Base: WACC=12.5%, TGR=2.0%. Bull: WACC=9.0%, TGR=3.5%.
A17: Comps Implied Share Price
A18: Comparable Company Analysis – Implied Share Price
A19: Metric | B19: 25th Pctile | C19: Median | D19: 75th Pctile
A20: EV / Revenue | B20: =('Comparable Companies '!G11*4040.65-1483.495)/54.208 -> 48.663813 | C20: =('Comparable Companies '!G13*4040.65-1483.495)/54.208 -> 94.505751 | D20: =('Comparable Companies '!G14*4040.65-1483.495)/54.208 -> 167.18199
A21: EV / EBITDA | B21: =('Comparable Companies '!H11*966.91-1483.495)/54.208 -> 129.68838 | C21: =('Comparable Companies '!H13*966.91-1483.495)/54.208 -> 147.88215 | D21: =('Comparable Companies '!H14*966.91-1483.495)/54.208 -> 203.93504
A22: P/E (Normalized) | B22: ='Comparable Companies '!I11*682.88/54.208 -> 198.62955 | C22: ='Comparable Companies '!I13*682.88/54.208 -> 214.47078 | D22: ='Comparable Companies '!I14*682.88/54.208 -> 445.91656
A23: Source: PitchBook market data; trading multiples as of March 27, 2026. Normalized P/E excludes FY2025 goodwill impairment.
A24: Football Field – Valuation Range ($ per Share)
A25: Football Field – Implied Share Price Range ($ per Share)
A26: Methodology | B26: Low | C26: High | D26: Source
A27: DCF (Bear / Bull) | B27: =IFERROR(DCF!I55,0) -> 92.50138 | C27: =IFERROR(DCF!C60,0) -> 232.56266 | D27: DCF model; WACC 9-14%, TGR 1-3.5%
A28: EV/EBITDA Comps | B28: =('Comparable Companies '!H11*966.91-1483.495)/54.208 -> 129.68838 | C28: =('Comparable Companies '!H14*966.91-1483.495)/54.208 -> 203.93504 | D28: PitchBook; 6 comps; 25th-75th pctile
A29: EV/Revenue Comps | B29: =('Comparable Companies '!G11*4040.65-1483.495)/54.208 -> 48.663813 | C29: =('Comparable Companies '!G14*4040.65-1483.495)/54.208 -> 167.18199 | D29: PitchBook; 6 comps; 25th-75th pctile
A30: 52-Week Range | B30: 61.45 | C30: 149.7 | D30: Yahoo Finance; 52-week range as of Mar 27 2026
A31: Analyst Price Targets | B31: 85 | C31: 145 | D31: Bloomberg consensus; 12 analysts
A32: Current Share Price (March 27, 2026) | B32: 79.54 | C32: 79.54
A34: INVESTMENT RECOMMENDATION
A35: BUY | Target Price: $117 | Implied Upside: +47% | Current Price: $79.54
A36: Thesis: CROX is currently trading at a huge discount to its real value (5.5x EV/EBITDA vs. a 9.8x median for peers) mainly because of temporary HEYDUDE-related problems. The main Crocs brand is still growing internationally by 11% and generating strong FCF ($659M in FY2025). With debt reduction on the calendar and margin improvements, we firmly believe there is a route to $117 in 12 months.

Sheet Comparable Companies 
A1: Crocs, Inc. (CROX)
A2: Comparable Company Analysis (Comps) – Trading Multiples ($ in millions unless noted)
A4: Company | B4: Ticker | C4: Mkt Cap ($M) | D4: Enterprise Value ($M) | E4: Revenue LTM ($M) | F4: EBITDA LTM ($M) | G4: EV / Revenue | H4: EV / EBITDA | I4: P/E LTM
A5: Steve Madden | B5: SHOO | C5: 2410 | D5: 2820 | E5: 2530 | F5: 203.76 | G5: 1.11 | H5: 13.86 | I5: 52.7
A6: Wolverine World Wide | B6: WWW | C6: 1290 | D6: 1860 | E6: 1870 | F6: 199.1 | G6: 0.99 | H6: 9.36 | I6: 17.12
A7: Columbia Sportswear | B7: COLM | C7: 2860 | D7: 2550 | E7: 3400 | F7: 295.39 | G7: 0.75 | H7: 8.62 | I7: 16.93
A8: Deckers Outdoor | B8: DECK | C8: 13350 | D8: 11610 | E8: 5370 | F8: 1350 | G8: 2.16 | H8: 8.57 | I8: 15.38
A9: On Holding | B9: ONON | C9: 10720 | D9: 10020 | E9: 3630 | F9: 695.24 | G9: 2.76 | H9: 14.41 | I9: 41.49
A10: Birkenstock | B10: BIRK | C10: 6290 | D10: 7600 | E10: 2410 | F10: 738.67 | G10: 3.15 | H10: 10.29 | I10: 14.57
A11: 25th Percentile | C11: =QUARTILE(C5:C10,1) -> 2522.5 | D11: =QUARTILE(D5:D10,1) -> 2617.5 | E11: =QUARTILE(E5:E10,1) -> 2440 | F11: =QUARTILE(F5:F10,1) -> 226.6675 | G11: =QUARTILE(G5:G10,1) -> 1.02 | H11: =QUARTILE(H5:H10,1) -> 8.805 | I11: =QUARTILE(I5:I10,1) -> 15.7675
A12: Mean | C12: =AVERAGE(C5:C10) -> 6153.3333 | D12: =AVERAGE(D5:D10) -> 6076.6667 | E12: =AVERAGE(E5:E10) -> 3201.6667 | F12: =AVERAGE(F5:F10) -> 580.36 | G12: =AVERAGE(G5:G10) -> 1.82 | H12: =AVERAGE(H5:H10) -> 10.851667 | I12: =AVERAGE(I5:I10) -> 26.365
A13: Median | C13: =MEDIAN(C5:C10) -> 4575 | D13: =MEDIAN(D5:D10) -> 5210 | E13: =MEDIAN(E5:E10) -> 2965 | F13: =MEDIAN(F5:F10) -> 495.315 | G13: =MEDIAN(G5:G10) -> 1.635 | H13: =MEDIAN(H5:H10) -> 9.825 | I13: =MEDIAN(I5:I10) -> 17.025
A14: 75th Percentile | C14: =QUARTILE(C5:C10,3) -> 9612.5 | D14: =QUARTILE(D5:D10,3) -> 9415 | E14: =QUARTILE(E5:E10,3) -> 3572.5 | F14: =QUARTILE(F5:F10,3) -> 727.8125 | G14: =QUARTILE(G5:G10,3) -> 2.61 | H14: =QUARTILE(H5:H10,3) -> 12.9675 | I14: =QUARTILE(I5:I10,3) -> 35.3975
A16: Crocs, Inc. (CROX) – Current Trading | C16: 4000 | D16: 5480 | E16: 4040.65 | F16: 966.91 | G16: 1.36 | H16: 5.54 | I16: 34.19
A18: Implied Valuation from Trading Comps
A19: Metric | B19: Median Multiple | C19: LTM Metric ($M) | D19: Implied EV ($M) | E19: Net Debt ($M) | F19: Implied Equity ($M) | G19: Imp. $/Share
A20: EV / Revenue | B20: =G13 -> 1.635 | C20: =E16 -> 4040.65 | D20: =B20*C20 -> 6606.4628 | E20: =('Balance Sheet'!H27+'Balance Sheet'!H32-'Balance Sheet'!H8)/1000 -> 1483.495 | F20: =D20-E20 -> 5122.9678 | G20: =F20/54.21 -> 94.502264
A21: EV / EBITDA | B21: =H13 -> 9.825 | C21: =F16 -> 966.91 | D21: =B21*C21 -> 9499.8907 | E21: =E20 -> 1483.495 | F21: =D21-E21 -> 8016.3957 | G21: =F21/54.21 -> 147.8767
A22: P/E | B22: =I13 -> 17.025 | C22: 682.88 | D22: N/M | E22: N/M | F22: =B22*C22 -> 11626.032 | G22: =F22/54.21 -> 214.46287
A24: Note: LTM = Last-twelve-months. Source: PitchBook / Yahoo Finance / SEC

Sheet Financial Ratios
A1: Crocs, Inc. (CROX)
A2: Financial Ratios Summary
A4: Fiscal Year | C4: 2020 | D4: 2021 | E4: 2022 | F4: 2023 | G4: 2024 | H4: 2025E | I4: 2026E | J4: 2027E | K4: 2028E | L4: 2029E
A5: PROFITABILITY
A6: Gross Margin | C6: ='Income Statement'!C12/'Income Statement'!C6 -> 0.54110715 | D6: ='Income Statement'!D12/'Income Statement'!D6 -> 0.61390602 | E6: ='Income Statement'!E12/'Income Statement'!E6 -> 0.52328828 | F6: ='Income Statement'!F12/'Income Statement'!F6 -> 0.55775277 | G6: ='Income Statement'!G12/'Income Statement'!G6 -> 0.58756571 | H6: ='Income Statement'!H12/'Income Statement'!H6 -> 0.58333604 | I6: ='Income Statement'!I12/'Income Statement'!I6 -> 0.585 | J6: ='Income Statement'!J12/'Income Statement'!J6 -> 0.587 | ... L6: ='Income Statement'!L12/'Income Statement'!L6 -> 0.592 | M6: Source: Crocs 10-K FY2020-2025; Model IS projections
A7: EBITDA Margin | C7: ='Income Statement'!C31/'Income Statement'!C6 -> 0.18962719 | D7: ='Income Statement'!D31/'Income Statement'!D6 -> 0.30908406 | E7: ='Income Statement'!E31/'Income Statement'!E6 -> 0.25034845 | F7: ='Income Statement'!F31/'Income Statement'!F6 -> 0.27770763 | G7: ='Income Statement'!G31/'Income Statement'!G6 -> 0.27201453 | H7: ='Income Statement'!H31/'Income Statement'!H6 -> 0.23929633 | I7: ='Income Statement'!I31/'Income Statement'!I6 -> 0.235 | J7: ='Income Statement'!J31/'Income Statement'!J6 -> 0.242 | ... L7: ='Income Statement'!L31/'Income Statement'!L6 -> 0.257
A8: EBIT Margin | C8: ='Income Statement'!C20/'Income Statement'!C6 -> 0.16969936 | D8: ='Income Statement'!D20/'Income Statement'!D6 -> 0.29526207 | E8: ='Income Statement'!E20/'Income Statement'!E6 -> 0.23931353 | F8: ='Income Statement'!F20/'Income Statement'!F6 -> 0.26400262 | G8: ='Income Statement'!G20/'Income Statement'!G6 -> 0.25498914 | H8: ='Income Statement'!H20/'Income Statement'!H6 -> 0.21967522 | I8: ='Income Statement'!I20/'Income Statement'!I6 -> 0.215 | J8: ='Income Statement'!J20/'Income Statement'!J6 -> 0.222 | ... L8: ='Income Statement'!L20/'Income Statement'!L6 -> 0.237
A9: Net Profit Margin | C9: ='Income Statement'!C28/'Income Statement'!C6 -> 0.22573742 | D9: ='Income Statement'!D28/'Income Statement'!D6 -> 0.31368937 | E9: ='Income Statement'!E28/'Income Statement'!E6 -> 0.1519441 | F9: ='Income Statement'!F28/'Income Statement'!F6 -> 0.20002438 | G9: ='Income Statement'!G28/'Income Statement'!G6 -> 0.23160555 | H9: ='Income Statement'!H28/'Income Statement'!H6 -> -0.020095297 | I9: ='Income Statement'!I28/'Income Statement'!I6 -> 0.15225487 | J9: ='Income Statement'!J28/'Income Statement'!J6 -> 0.1595078 | ... L9: ='Income Statement'!L28/'Income Statement'!L6 -> 0.17513563
A10: Return on Assets (ROA) | C10: ='Income Statement'!C28/'Balance Sheet'!C20 -> 0.27965904 | D10: ='Income Statement'!D28/'Balance Sheet'!D20 -> 0.46968418 | E10: ='Income Statement'!E28/'Balance Sheet'!E20 -> 0.11998742 | F10: ='Income Statement'!F28/'Balance Sheet'!F20 -> 0.17067061 | G10: ='Income Statement'!G28/'Balance Sheet'!G20 -> 0.19743159 | H10: ='Income Statement'!H28/'Balance Sheet'!H20 -> -0.019449787 | I10: ='Income Statement'!I28/'Balance Sheet'!I20 -> 0.14856191 | J10: ='Income Statement'!J28/'Balance Sheet'!J20 -> 0.15917357 | ... L10: ='Income Statement'!L28/'Balance Sheet'!L20 -> 0.18184641
A11: Return on Equity (ROE) | C11: =IFERROR('Income Statement'!C28/'Balance Sheet'!C44,"N/M") -> 1.0764813 | D11: =IFERROR('Income Statement'!D28/'Balance Sheet'!D44,"N/M") -> 51.533447 | E11: =IFERROR('Income Statement'!E28/'Balance Sheet'!E44,"N/M") -> 0.66039678 | F11: =IFERROR('Income Statement'!F28/'Balance Sheet'!F44,"N/M") -> 0.5451224 | G11: =IFERROR('Income Statement'!G28/'Balance Sheet'!G44,"N/M") -> 0.51754341 | H11: =IFERROR('Income Statement'!H28/'Balance Sheet'!H44,"N/M") -> -0.062784402 | I11: =IFERROR('Income Statement'!I28/'Balance Sheet'!I44,"N/M") -> 0.45037232 | J11: =IFERROR('Income Statement'!J28/'Balance Sheet'!J44,"N/M") -> 0.44543475 | ... L11: =IFERROR('Income Statement'!L28/'Balance Sheet'!L44,"N/M") -> 0.41890828
A12: Return on Invested Capital (ROIC) | C12: =IFERROR('Income Statement'!C20*(1-0.215)/('Balance Sheet'!C44+'Balance Sheet'!C27+'Balance Sheet'!C32),"N/M") -> 0.2780133 | D12: =IFERROR('Income Statement'!D20*(1-0.215)/('Balance Sheet'!D44+'Balance Sheet'!D27+'Balance Sheet'!D32),"N/M") -> 0.54846845 | E12: =IFERROR('Income Statement'!E20*(1-0.215)/('Balance Sheet'!E44+'Balance Sheet'!E27+'Balance Sheet'!E32),"N/M") -> 0.19568239 | F12: =IFERROR('Income Statement'!F20*(1-0.215)/('Balance Sheet'!F44+'Balance Sheet'!F27+'Balance Sheet'!F32),"N/M") -> 0.2379993 | G12: =IFERROR('Income Statement'!G20*(1-0.215)/('Balance Sheet'!G44+'Balance Sheet'!G27+'Balance Sheet'!G32),"N/M") -> 0.23214532 | H12: =IFERROR('Income Statement'!H20*(1-0.215)/('Balance Sheet'!H44+'Balance Sheet'!H27+'Balance Sheet'!H32),"N/M") -> 0.2396828 | I12: =IFERROR('Income Statement'!I20*(1-0.215)/('Balance Sheet'!I44+'Balance Sheet'!I27+'Balance Sheet'!I32),"N/M") -> 0.23973562 | J12: =IFERROR('Income Statement'!J20*(1-0.215)/('Balance Sheet'!J44+'Balance Sheet'!J27+'Balance Sheet'!J32),"N/M") -> 0.25504722 | ... L12: =IFERROR('Income Statement'!L20*(1-0.215)/('Balance Sheet'!L44+'Balance Sheet'!L27+'Balance Sheet'!L32),"N/M") -> 0.28420536
A14: LIQUIDITY
A15: Current Ratio | C15: ='Balance Sheet'!C12/'Balance Sheet'!C29 -> 1.6902196 | D15: ='Balance Sheet'!D12/'Balance Sheet'!D29 -> 1.7168861 | E15: ='Balance Sheet'!E12/'Balance Sheet'!E29 -> 1.5999011 | F15: ='Balance Sheet'!F12/'Balance Sheet'!F29 -> 1.3041805 | G15: ='Balance Sheet'!G12/'Balance Sheet'!G29 -> 1.1784107 | H15: ='Balance Sheet'!H12/'Balance Sheet'!H29 -> 1.265314 | I15: ='Balance Sheet'!I12/'Balance Sheet'!I29 -> 1.1729194 | J15: ='Balance Sheet'!J12/'Balance Sheet'!J29 -> 1.1350839 | ... L15: ='Balance Sheet'!L12/'Balance Sheet'!L29 -> 1.2668031 | M15: Source: Crocs 10-K FY2020-2025; Model BS/CFS projections
A16: Quick Ratio | C16: =('Balance Sheet'!C12-'Balance Sheet'!C10)/'Balance Sheet'!C29 -> 1.0896345 | D16: =('Balance Sheet'!D12-'Balance Sheet'!D10)/'Balance Sheet'!D29 -> 1.1669212 | E16: =('Balance Sheet'!E12-'Balance Sheet'!E10)/'Balance Sheet'!E29 -> 0.86456647 | F16: =('Balance Sheet'!F12-'Balance Sheet'!F10)/'Balance Sheet'!F29 -> 0.75276101 | G16: =('Balance Sheet'!G12-'Balance Sheet'!G10)/'Balance Sheet'!G29 -> 0.69712162 | H16: =('Balance Sheet'!H12-'Balance Sheet'!H10)/'Balance Sheet'!H29 -> 0.73871529 | I16: =('Balance Sheet'!I12-'Balance Sheet'!I10)/'Balance Sheet'!I29 -> 0.67109199 | J16: =('Balance Sheet'!J12-'Balance Sheet'!J10)/'Balance Sheet'!J29 -> 0.63389904 | ... L16: =('Balance Sheet'!L12-'Balance Sheet'!L10)/'Balance Sheet'!L29 -> 0.76529465
A17: Cash Ratio | C17: ='Balance Sheet'!C8/'Balance Sheet'!C29 -> 0.46573886 | D17: ='Balance Sheet'!D8/'Balance Sheet'!D29 -> 0.54913289 | E17: ='Balance Sheet'!E8/'Balance Sheet'!E29 -> 0.29882546 | F17: ='Balance Sheet'!F8/'Balance Sheet'!F29 -> 0.21378899 | G17: ='Balance Sheet'!G8/'Balance Sheet'!G29 -> 0.24383011 | H17: ='Balance Sheet'!H8/'Balance Sheet'!H29 -> 0.18618569 | I17: ='Balance Sheet'!I8/'Balance Sheet'!I29 -> 0.16015713 | J17: ='Balance Sheet'!J8/'Balance Sheet'!J29 -> 0.12114735 | ... L17: ='Balance Sheet'!L8/'Balance Sheet'!L29 -> 0.24592405
A18: Operating Cash Flow Ratio | C18: ='Cash Flow Statement'!C19/'Balance Sheet'!C29 -> 0.91535201 | D18: ='Cash Flow Statement'!D19/'Balance Sheet'!D29 -> 1.4608505 | E18: ='Cash Flow Statement'!E19/'Balance Sheet'!E29 -> 0.94053712 | F18: ='Cash Flow Statement'!F19/'Balance Sheet'!F29 -> 1.3324493 | G18: ='Cash Flow Statement'!G19/'Balance Sheet'!G29 -> 1.3408204 | H18: ='Cash Flow Statement'!H19/'Balance Sheet'!H29 -> 1.0147144 | I18: ='Cash Flow Statement'!I19/'Balance Sheet'!I29 -> 1.0720111 | J18: ='Cash Flow Statement'!J19/'Balance Sheet'!J29 -> 1.0488383 | ... L18: ='Cash Flow Statement'!L19/'Balance Sheet'!L29 -> 1.1449251
A20: LEVERAGE / SOLVENCY
A21: Debt-to-Equity (D/E) | C21: =IFERROR(('Balance Sheet'!C27+'Balance Sheet'!C32)/'Balance Sheet'!C44,"N/M") -> 1.2850055 | D21: =IFERROR(('Balance Sheet'!D27+'Balance Sheet'!D32)/'Balance Sheet'!D44,"N/M") -> 68.424869 | E21: =IFERROR(('Balance Sheet'!E27+'Balance Sheet'!E32)/'Balance Sheet'!E44,"N/M") -> 3.1725952 | F21: =IFERROR(('Balance Sheet'!F27+'Balance Sheet'!F32)/'Balance Sheet'!F44,"N/M") -> 1.3730851 | G21: =IFERROR(('Balance Sheet'!G27+'Balance Sheet'!G32)/'Balance Sheet'!G44,"N/M") -> 0.92676709 | H21: =IFERROR(('Balance Sheet'!H27+'Balance Sheet'!H32)/'Balance Sheet'!H44,"N/M") -> 1.24787 | I21: =IFERROR(('Balance Sheet'!I27+'Balance Sheet'!I32)/'Balance Sheet'!I44,"N/M") -> 1.082457 | J21: =IFERROR(('Balance Sheet'!J27+'Balance Sheet'!J32)/'Balance Sheet'!J44,"N/M") -> 0.90811353 | ... L21: =IFERROR(('Balance Sheet'!L27+'Balance Sheet'!L32)/'Balance Sheet'!L44,"N/M") -> 0.56577794 | M21: Source: Crocs 10-K FY2020-2025; PitchBook interest expense data
A22: Debt-to-Total Capital | C22: =IFERROR(('Balance Sheet'!C27+'Balance Sheet'!C32)/('Balance Sheet'!C27+'Balance Sheet'!C32+'Balance Sheet'!C44),"N/M") -> 0.56236429 | D22: =IFERROR(('Balance Sheet'!D27+'Balance Sheet'!D32)/('Balance Sheet'!D27+'Balance Sheet'!D32+'Balance Sheet'!D44),"N/M") -> 0.98559594 | E22: =IFERROR(('Balance Sheet'!E27+'Balance Sheet'!E32)/('Balance Sheet'!E27+'Balance Sheet'!E32+'Balance Sheet'!E44),"N/M") -> 0.760341 | F22: =IFERROR(('Balance Sheet'!F27+'Balance Sheet'!F32)/('Balance Sheet'!F27+'Balance Sheet'!F32+'Balance Sheet'!F44),"N/M") -> 0.57860761 | G22: =IFERROR(('Balance Sheet'!G27+'Balance Sheet'!G32)/('Balance Sheet'!G27+'Balance Sheet'!G32+'Balance Sheet'!G44),"N/M") -> 0.48099591 | H22: =IFERROR(('Balance Sheet'!H27+'Balance Sheet'!H32)/('Balance Sheet'!H27+'Balance Sheet'!H32+'Balance Sheet'!H44),"N/M") -> 0.55513441 | I22: =IFERROR(('Balance Sheet'!I27+'Balance Sheet'!I32)/('Balance Sheet'!I27+'Balance Sheet'!I32+'Balance Sheet'!I44),"N/M") -> 0.51979802 | J22: =IFERROR(('Balance Sheet'!J27+'Balance Sheet'!J32)/('Balance Sheet'!J27+'Balance Sheet'!J32+'Balance Sheet'!J44),"N/M") -> 0.47592217 | ... L22: =IFERROR(('Balance Sheet'!L27+'Balance Sheet'!L32)/('Balance Sheet'!L27+'Balance Sheet'!L32+'Balance Sheet'!L44),"N/M") -> 0.36133983
A23: Net Debt / EBITDA | C23: =IFERROR(('Balance Sheet'!C27+'Balance Sheet'!C32-'Balance Sheet'!C8)/'Income Statement'!C31,"N/M") -> 0.90430114 | D23: =IFERROR(('Balance Sheet'!D27+'Balance Sheet'!D32-'Balance Sheet'!D8)/'Income Statement'!D31,"N/M") -> 1.0493986 | E23: =IFERROR(('Balance Sheet'!E27+'Balance Sheet'!E32-'Balance Sheet'!E8)/'Income Statement'!E31,"N/M") -> 2.7004219 | F23: =IFERROR(('Balance Sheet'!F27+'Balance Sheet'!F32-'Balance Sheet'!F8)/'Income Statement'!F31,"N/M") -> 1.6785856 | G23: =IFERROR(('Balance Sheet'!G27+'Balance Sheet'!G32-'Balance Sheet'!G8)/'Income Statement'!G31,"N/M") -> 1.3629378 | H23: =IFERROR(('Balance Sheet'!H27+'Balance Sheet'!H32-'Balance Sheet'!H8)/'Income Statement'!H31,"N/M") -> 1.5342606 | I23: =IFERROR(('Balance Sheet'!I27+'Balance Sheet'!I32-'Balance Sheet'!I8)/'Income Statement'!I31,"N/M") -> 1.4352076 | J23: =IFERROR(('Balance Sheet'!J27+'Balance Sheet'!J32-'Balance Sheet'!J8)/'Income Statement'!J31,"N/M") -> 1.2544765 | ... L23: =IFERROR(('Balance Sheet'!L27+'Balance Sheet'!L32-'Balance Sheet'!L8)/'Income Statement'!L31,"N/M") -> 0.7518889
A24: Interest Coverage (EBIT / Int. Exp.) | C24: =IFERROR('Income Statement'!C20/6742,"N/M") -> 34.885049 | D24: =IFERROR('Income Statement'!D20/21647,"N/M") -> 31.554673 | E24: =IFERROR('Income Statement'!E20/136158,"N/M") -> 6.2482998 | F24: =IFERROR('Income Statement'!F20/161351,"N/M") -> 6.483195 | G24: =IFERROR('Income Statement'!G20/109264,"N/M") -> 9.5730799 | H24: =IFERROR('Income Statement'!H20/88287,"N/M") -> 10.053915 | I24: =IFERROR('Income Statement'!I20/ABS('Income Statement'!I23),"N/M") -> 10.216325 | J24: =IFERROR('Income Statement'!J20/ABS('Income Statement'!J23),"N/M") -> 11.805151 | K24: =IFERROR('Income Statement'!K20/ABS('Income Statement'!K23),"N/M") -> 14.054226 | L24: =IFERROR('Income Statement'!L20/ABS('Income Statement'!L23),"N/M") -> 17.053696
A25: Debt Service Coverage Ratio | C25: =IFERROR('Cash Flow Statement'!C19/('Balance Sheet'!C27+'Balance Sheet'!C32),"N/M") -> 0.71466402 | D25: =IFERROR('Cash Flow Statement'!D19/('Balance Sheet'!D27+'Balance Sheet'!D32),"N/M") -> 0.58861471 | E25: =IFERROR('Cash Flow Statement'!E19/('Balance Sheet'!E27+'Balance Sheet'!E32),"N/M") -> 0.23242789 | F25: =IFERROR('Cash Flow Statement'!F19/('Balance Sheet'!F27+'Balance Sheet'!F32),"N/M") -> 0.46607025 | G25: =IFERROR('Cash Flow Statement'!G19/('Balance Sheet'!G27+'Balance Sheet'!G32),"N/M") -> 0.58337056 | H25: =IFERROR('Cash Flow Statement'!H19/('Balance Sheet'!H27+'Balance Sheet'!H32),"N/M") -> 0.44020909 | I25: =IFERROR('Cash Flow Statement'!I19/('Balance Sheet'!I27+'Balance Sheet'!I32),"N/M") -> 0.52434488 | J25: =IFERROR('Cash Flow Statement'!J19/('Balance Sheet'!J27+'Balance Sheet'!J32),"N/M") -> 0.57525042 | ... L25: =IFERROR('Cash Flow Statement'!L19/('Balance Sheet'!L27+'Balance Sheet'!L32),"N/M") -> 0.85229824
A27: EFFICIENCY / ACTIVITY
A28: Asset Turnover | C28: ='Income Statement'!C6/'Balance Sheet'!C20 -> 1.2388688 | D28: ='Income Statement'!D6/'Balance Sheet'!D20 -> 1.4972907 | E28: ='Income Statement'!E6/'Balance Sheet'!E20 -> 0.78968132 | F28: ='Income Statement'!F6/'Balance Sheet'!F20 -> 0.85324906 | G28: ='Income Statement'!G6/'Balance Sheet'!G20 -> 0.85244754 | H28: ='Income Statement'!H6/'Balance Sheet'!H20 -> 0.9678776 | I28: ='Income Statement'!I6/'Balance Sheet'!I20 -> 0.97574487 | J28: ='Income Statement'!J6/'Balance Sheet'!J20 -> 0.99790459 | ... L28: ='Income Statement'!L6/'Balance Sheet'!L20 -> 1.0383176 | M28: Source: Crocs 10-K FY2020-2025; Model BS/IS projections
A29: Inventory Turnover | C29: ='Income Statement'!C9/'Balance Sheet'!C10 -> 3.6317917 | D29: ='Income Statement'!D9/'Balance Sheet'!D10 -> 4.183196 | E29: ='Income Statement'!E9/'Balance Sheet'!E10 -> 3.5938912 | F29: ='Income Statement'!F9/'Balance Sheet'!F10 -> 4.5508864 | G29: ='Income Statement'!G9/'Balance Sheet'!G10 -> 4.7489993 | H29: ='Income Statement'!H9/'Balance Sheet'!H10 -> 4.5664534 | I29: ='Income Statement'!I9/'Balance Sheet'!I10 -> 4.6202532 | J29: ='Income Statement'!J9/'Balance Sheet'!J10 -> 4.6202532 | ... L29: ='Income Statement'!L9/'Balance Sheet'!L10 -> 4.6202532
A30: Days Sales Outstanding (DSO) | C30: ='Balance Sheet'!C9/'Income Statement'!C6*365 -> 42.800792 | D30: ='Balance Sheet'!D9/'Income Statement'!D6*365 -> 34.265964 | E30: ='Balance Sheet'!E9/'Income Statement'!E6*365 -> 33.798629 | F30: ='Balance Sheet'!F9/'Income Statement'!F6*365 -> 30.512046 | G30: ='Balance Sheet'!G9/'Income Statement'!G6*365 -> 25.261659 | H30: ='Balance Sheet'!H9/'Income Statement'!H6*365 -> 30.085547 | I30: ='Balance Sheet'!I9/'Income Statement'!I6*365 -> 29 | J30: ='Balance Sheet'!J9/'Income Statement'!J6*365 -> 29 | ... L30: ='Balance Sheet'!L9/'Income Statement'!L6*365 -> 29
A31: Days Inventory Held (DIH) | C31: ='Balance Sheet'!C10/'Income Statement'!C9*365 -> 100.50136 | D31: ='Balance Sheet'!D10/'Income Statement'!D9*365 -> 87.253861 | E31: ='Balance Sheet'!E10/'Income Statement'!E9*365 -> 101.56123 | F31: ='Balance Sheet'!F10/'Income Statement'!F9*365 -> 80.204156 | G31: ='Balance Sheet'!G10/'Income Statement'!G9*365 -> 76.858297 | H31: ='Balance Sheet'!H10/'Income Statement'!H9*365 -> 79.93074 | I31: ='Balance Sheet'!I10/'Income Statement'!I9*365 -> 79 | J31: ='Balance Sheet'!J10/'Income Statement'!J9*365 -> 79 | ... L31: ='Balance Sheet'!L10/'Income Statement'!L9*365 -> 79
A32: Days Payable Outstanding (DPO) | C32: ='Balance Sheet'!C24/'Income Statement'!C9*365 -> 78.365589 | D32: ='Balance Sheet'!D24/'Income Statement'!D9*365 -> 81.278656 | E32: ='Balance Sheet'!E24/'Income Statement'!E9*365 -> 77.063819 | F32: ='Balance Sheet'!F24/'Income Statement'!F9*365 -> 73.048032 | G32: ='Balance Sheet'!G24/'Income Statement'!G9*365 -> 84.33693 | H32: ='Balance Sheet'!H24/'Income Statement'!H9*365 -> 72.94528 | I32: ='Balance Sheet'!I24/'Income Statement'!I9*365 -> 77 | J32: ='Balance Sheet'!J24/'Income Statement'!J9*365 -> 77 | ... L32: ='Balance Sheet'!L24/'Income Statement'!L9*365 -> 77
A33: Cash Conversion Cycle (CCC) | C33: =C30+C31-C32 -> 64.93656 | D33: =D30+D31-D32 -> 40.24117 | E33: =E30+E31-E32 -> 58.296037 | F33: =F30+F31-F32 -> 37.66817 | G33: =G30+G31-G32 -> 17.783027 | H33: =H30+H31-H32 -> 37.071007 | I33: =I30+I31-I32 -> 31 | J33: =J30+J31-J32 -> 31 | ... L33: =L30+L31-L32 -> 31
A34: Receivables Turnover | C34: ='Income Statement'!C6/'Balance Sheet'!C9 -> 8.5278796 | D34: ='Income Statement'!D6/'Balance Sheet'!D9 -> 10.651969 | E34: ='Income Statement'!E6/'Balance Sheet'!E9 -> 10.799255 | F34: ='Income Statement'!F6/'Balance Sheet'!F9 -> 11.962488 | G34: ='Income Statement'!G6/'Balance Sheet'!G9 -> 14.448774 | H34: ='Income Statement'!H6/'Balance Sheet'!H9 -> 12.132071 | I34: ='Income Statement'!I6/'Balance Sheet'!I9 -> 12.586207 | J34: ='Income Statement'!J6/'Balance Sheet'!J9 -> 12.586207 | ... L34: ='Income Statement'!L6/'Balance Sheet'!L9 -> 12.586207
A36: VALUATION
A37: Price / Earnings (P/E) | C37: =IFERROR(4311724/('Income Statement'!C28),"N/M") -> 13.781596 | D37: =IFERROR(4311724/('Income Statement'!D28),"N/M") -> 5.9415181 | E37: =IFERROR(4311724/('Income Statement'!E28),"N/M") -> 7.9823237 | F37: =IFERROR(4311724/('Income Statement'!F28),"N/M") -> 5.4402081 | G37: =IFERROR(4311724/('Income Statement'!G28),"N/M") -> 4.5383177 | H37: =IFERROR(4311724/('Income Statement'!H28),"N/M") -> -53.101357 | I37: =IFERROR(4311724/('Income Statement'!I28),"N/M") -> 7.0793543 | J37: =IFERROR(4311724/('Income Statement'!J28),"N/M") -> 6.6905458 | ... L37: =IFERROR(4311724/('Income Statement'!L28),"N/M") -> 5.7438718 | M37: Source: Yahoo Finance Mar 27 2026 price $79.54; PitchBook market data. Note: valuation multiples use current EV/price applied to each year IS for trend analysis.
A38: Price / Book (P/B) | C38: =IFERROR(4311724/'Balance Sheet'!C44,"N/M") -> 14.835631 | D38: =IFERROR(4311724/'Balance Sheet'!D44,"N/M") -> 306.18691 | E38: =IFERROR(4311724/'Balance Sheet'!E44,"N/M") -> 5.2715009 | F38: =IFERROR(4311724/'Balance Sheet'!F44,"N/M") -> 2.9655793 | G38: =IFERROR(4311724/'Balance Sheet'!G44,"N/M") -> 2.3487764 | H38: =IFERROR(4311724/'Balance Sheet'!H44,"N/M") -> 3.333937 | I38: =IFERROR(4311724/'Balance Sheet'!I44,"N/M") -> 3.1883453 | J38: =IFERROR(4311724/'Balance Sheet'!J44,"N/M") -> 2.9802016 | ... L38: =IFERROR(4311724/'Balance Sheet'!L44,"N/M") -> 2.4061555
A39: EV / Revenue | C39: =5796339/'Income Statement'!C6 -> 4.1822106 | D39: =5796339/'Income Statement'!D6 -> 2.5055325 | E39: =5796339/'Income Statement'!E6 -> 1.630482 | F39: =5796339/'Income Statement'!F6 -> 1.462855 | G39: =5796339/'Income Statement'!G6 -> 1.4130147 | H39: =5796339/'Income Statement'!H6 -> 1.4345076 | I39: =5796339/'Income Statement'!I6 -> 1.4489976 | J39: =5796339/'Income Statement'!J6 -> 1.4346511 | ... L39: =5796339/'Income Statement'!L6 -> 1.3523281
A40: EV / EBITDA | C40: =IFERROR(5796339/'Income Statement'!C31,"N/M") -> 22.05491 | D40: =IFERROR(5796339/'Income Statement'!D31,"N/M") -> 8.1063143 | E40: =IFERROR(5796339/'Income Statement'!E31,"N/M") -> 6.5128502 | F40: =IFERROR(5796339/'Income Statement'!F31,"N/M") -> 5.2676081 | G40: =IFERROR(5796339/'Income Statement'!G31,"N/M") -> 5.1946295 | H40: =IFERROR(5796339/'Income Statement'!H31,"N/M") -> 5.9946913 | I40: =IFERROR(5796339/'Income Statement'!I31,"N/M") -> 6.1659473 | J40: =IFERROR(5796339/'Income Statement'!J31,"N/M") -> 5.9283104 | ... L40: =IFERROR(5796339/'Income Statement'!L31,"N/M") -> 5.2619772
A41: EV / EBIT | C41: =IFERROR(5796339/'Income Statement'!C20,"N/M") -> 24.644822 | D41: =IFERROR(5796339/'Income Statement'!D20,"N/M") -> 8.485792 | E41: =IFERROR(5796339/'Income Statement'!E20,"N/M") -> 6.8131626 | F41: =IFERROR(5796339/'Income Statement'!F20,"N/M") -> 5.5410623 | G41: =IFERROR(5796339/'Income Statement'!G20,"N/M") -> 5.5414702 | H41: =IFERROR(5796339/'Income Statement'!H20,"N/M") -> 6.5301297 | I41: =IFERROR(5796339/'Income Statement'!I20,"N/M") -> 6.7395238 | J41: =IFERROR(5796339/'Income Statement'!J20,"N/M") -> 6.4623924 | ... L41: =IFERROR(5796339/'Income Statement'!L20,"N/M") -> 5.7060259
A42: EV / FCF | C42: =IFERROR(5796339/('Cash Flow Statement'!C19+'Cash Flow Statement'!C22),"N/M") -> 25.776514 | D42: =IFERROR(5796339/('Cash Flow Statement'!D19+'Cash Flow Statement'!D22),"N/M") -> 11.337605 | E42: =IFERROR(5796339/('Cash Flow Statement'!E19+'Cash Flow Statement'!E22),"N/M") -> 11.617027 | F42: =IFERROR(5796339/('Cash Flow Statement'!F19+'Cash Flow Statement'!F22),"N/M") -> 7.1136522 | G42: =IFERROR(5796339/('Cash Flow Statement'!G19+'Cash Flow Statement'!G22),"N/M") -> 6.278945 | H42: =IFERROR(5796339/('Cash Flow Statement'!H19+'Cash Flow Statement'!H22),"N/M") -> 8.79299 | I42: =IFERROR(5796339/('Cash Flow Statement'!I19+'Cash Flow Statement'!I22),"N/M") -> 8.3333726 | J42: =IFERROR(5796339/('Cash Flow Statement'!J19+'Cash Flow Statement'!J22),"N/M") -> 8.4857445 | ... L42: =IFERROR(5796339/('Cash Flow Statement'!L19+'Cash Flow Statement'!L22),"N/M") -> 7.3655723
A43: Dividend Yield | C43: N/A | D43: N/A | E43: N/A | F43: N/A | G43: N/A | H43: N/A | I43: N/A | J43: N/A | K43: N/A | L43: N/A
A45: GROWTH
A46: Revenue Growth YoY | C46: N/A | D46: ='Income Statement'!D6/'Income Statement'!C6-1 -> 0.66919032 | E46: ='Income Statement'!E6/'Income Statement'!D6-1 -> 0.53668212 | F46: ='Income Statement'!F6/'Income Statement'!E6-1 -> 0.11458895 | G46: ='Income Statement'!G6/'Income Statement'!F6-1 -> 0.035272277 | H46: ='Income Statement'!H6/'Income Statement'!G6-1 -> -0.014982784 | I46: ='Income Statement'!I6/'Income Statement'!H6-1 -> -0.01 | J46: ='Income Statement'!J6/'Income Statement'!I6-1 -> 0.01 | K46: ='Income Statement'!K6/'Income Statement'!J6-1 -> 0.025 | L46: ='Income Statement'!L6/'Income Statement'!K6-1 -> 0.035 | M46: Source: Crocs 10-K FY2020-2025; Model projections
A47: EBITDA Growth YoY | C47: N/A | D47: =IFERROR('Income Statement'!D31/'Income Statement'!C31-1,"N/M") -> 1.7207074 | E47: =IFERROR('Income Statement'!E31/'Income Statement'!D31-1,"N/M") -> 0.24466463 | F47: =IFERROR('Income Statement'!F31/'Income Statement'!E31-1,"N/M") -> 0.23639612 | G47: =IFERROR('Income Statement'!G31/'Income Statement'!F31-1,"N/M") -> 0.01404886 | H47: =IFERROR('Income Statement'!H31/'Income Statement'!G31-1,"N/M") -> -0.13346173 | I47: =IFERROR('Income Statement'!I31/'Income Statement'!H31-1,"N/M") -> -0.027774477 | J47: =IFERROR('Income Statement'!J31/'Income Statement'!I31-1,"N/M") -> 0.040085106 | K47: =IFERROR('Income Statement'!K31/'Income Statement'!J31-1,"N/M") -> 0.058884298 | L47: =IFERROR('Income Statement'!L31/'Income Statement'!K31-1,"N/M") -> 0.06398
A48: Net Income Growth YoY | C48: N/A | D48: =IFERROR(IF('Income Statement'!C28<0,"N/M",'Income Statement'!D28/'Income Statement'!C28-1),"N/M") -> 1.3195413 | E48: =IFERROR(IF('Income Statement'!D28<0,"N/M",'Income Statement'!E28/'Income Statement'!D28-1),"N/M") -> -0.25566561 | F48: =IFERROR(IF('Income Statement'!E28<0,"N/M",'Income Statement'!F28/'Income Statement'!E28-1),"N/M") -> 0.46728278 | G48: =IFERROR(IF('Income Statement'!F28<0,"N/M",'Income Statement'!G28/'Income Statement'!F28-1),"N/M") -> 0.19872793 | H48: =IFERROR(IF('Income Statement'!G28<0,"N/M",'Income Statement'!H28/'Income Statement'!G28-1),"N/M") -> -1.0854652 | I48: =IFERROR(IF('Income Statement'!H28<0,"N/M",'Income Statement'!I28/'Income Statement'!H28-1),"N/M") -> N/M | J48: =IFERROR(IF('Income Statement'!I28<0,"N/M",'Income Statement'!J28/'Income Statement'!I28-1),"N/M") -> 0.058113129 | K48: =IFERROR(IF('Income Statement'!J28<0,"N/M",'Income Statement'!K28/'Income Statement'!J28-1),"N/M") -> 0.077664624 | L48: =IFERROR(IF('Income Statement'!K28<0,"N/M",'Income Statement'!L28/'Income Statement'!K28-1),"N/M") -> 0.080869303
A49: EPS Growth YoY | C49: N/A | D49: =IFERROR(IF('Income Statement'!C37<0,"N/M",'Income Statement'!D37/'Income Statement'!C37-1),"N/M") -> N/M | E49: =IFERROR(IF('Income Statement'!D37<0,"N/M",'Income Statement'!E37/'Income Statement'!D37-1),"N/M") -> N/M | F49: =IFERROR(IF('Income Statement'!E37<0,"N/M",'Income Statement'!F37/'Income Statement'!E37-1),"N/M") -> N/M | G49: =IFERROR(IF('Income Statement'!F37<0,"N/M",'Income Statement'!G37/'Income Statement'!F37-1),"N/M") -> N/M | H49: =IFERROR(IF('Income Statement'!G37<0,"N/M",'Income Statement'!H37/'Income Statement'!G37-1),"N/M") -> N/M | I49: =IFERROR(IF('Income Statement'!H37<0,"N/M",'Income Statement'!I37/'Income Statement'!H37-1),"N/M") -> N/M | J49: =IFERROR(IF('Income Statement'!I37<0,"N/M",'Income Statement'!J37/'Income Statement'!I37-1),"N/M") -> N/M | K49: =IFERROR(IF('Income Statement'!J37<0,"N/M",'Income Statement'!K37/'Income Statement'!J37-1),"N/M") -> N/M | L49: =IFERROR(IF('Income Statement'!K37<0,"N/M",'Income Statement'!L37/'Income Statement'!K37-1),"N/M") -> N/M
A50: FCF Growth YoY | C50: N/A | D50: =IFERROR(('Cash Flow Statement'!D19+'Cash Flow Statement'!D22)/('Cash Flow Statement'!C19+'Cash Flow Statement'!C22)-1,"N/M") -> 1.2735415 | E50: =IFERROR(('Cash Flow Statement'!E19+'Cash Flow Statement'!E22)/('Cash Flow Statement'!D19+'Cash Flow Statement'!D22)-1,"N/M") -> -0.024052859 | F50: =IFERROR(('Cash Flow Statement'!F19+'Cash Flow Statement'!F22)/('Cash Flow Statement'!E19+'Cash Flow Statement'!E22)-1,"N/M") -> 0.6330609 | G50: =IFERROR(('Cash Flow Statement'!G19+'Cash Flow Statement'!G22)/('Cash Flow Statement'!F19+'Cash Flow Statement'!F22)-1,"N/M") -> 0.1329375 | H50: =IFERROR(('Cash Flow Statement'!H19+'Cash Flow Statement'!H22)/('Cash Flow Statement'!G19+'Cash Flow Statement'!G22)-1,"N/M") -> -0.28591469 | I50: =IFERROR(('Cash Flow Statement'!I19+'Cash Flow Statement'!I22)/('Cash Flow Statement'!H19+'Cash Flow Statement'!H22)-1,"N/M") -> 0.055153831 | J50: =IFERROR(('Cash Flow Statement'!J19+'Cash Flow Statement'!J22)/('Cash Flow Statement'!I19+'Cash Flow Statement'!I22)-1,"N/M") -> -0.017956226 | K50: =IFERROR(('Cash Flow Statement'!K19+'Cash Flow Statement'!K22)/('Cash Flow Statement'!J19+'Cash Flow Statement'!J22)-1,"N/M") -> 0.070705275 | L50: =IFERROR(('Cash Flow Statement'!L19+'Cash Flow Statement'!L22)/('Cash Flow Statement'!K19+'Cash Flow Statement'!K22)-1,"N/M") -> 0.076003074
A52: Derived from Financial Statements; Blue = historical; Gray = projected

Sheet Assumptions 1
A1: Crocs, Inc. (CROX) – Assumptions Page: Income Statement & Cash Flow
A2: Yellow = input assumptions | Base = Scenario 1 | Upside = Scenario 2 | Downside = Scenario 3 | Amounts in % unless stated
D3: Projection Period | J3: Rationale | K3: Source
A4: Assumption | B4: Scenario | C4: # | D4: Year 1 2026 | E4: Year 2 2027 | F4: Year 3 2028 | G4: Year 4 2029 | H4: Year 5 2030
A5: Income Statement Assumptions
B6: Active | D6: =D7 -> -0.01 | E6: =E7 -> 0.01 | F6: =F7 -> 0.025 | G6: =G7 -> 0.035 | H6: =H7 -> 0.043
A7: Revenue Growth Rate (% YoY) | B7: Base | C7: 1 | D7: -0.01 | E7: 0.01 | F7: 0.025 | G7: 0.035 | H7: 0.043 | J7: 3yr CAGR FY2022-2025: 4.3%. Recent trend slowing — FY2025 actual (1.5%). Base: gradual recovery from management guided (1%) in FY2026 converging to industry CAGR 4.3% by 2030. Upside: HEYDUDE stabilization + international Crocs growth (11% in FY2025). Downside: prolonged HEYDUDE weakness + tariff headwinds + North America consumer pressure. | K7: Crocs 10-K FY2025 | Crocs 8-K Feb 2026 (FY2026 guidance) | Grand View Research (4.3% CAGR 2025-2030)
B8: Upside | C8: 2 | D8: 0.01 | E8: 0.03 | F8: 0.045 | G8: 0.055 | H8: 0.065
B9: Downside | C9: 3 | D9: -0.03 | E9: -0.02 | F9: -0.01 | G9: 0.005 | H9: 0.015
B11: Active | D11: =D12 -> 0.415 | E11: =E12 -> 0.413 | F11: =F12 -> 0.41 | G11: =G12 -> 0.408 | H11: =H12 -> 0.405
A12: Cost of Goods Sold (% of Revenue) | B12: Base | C12: 1 | D12: 0.415 | E12: 0.413 | F12: 0.41 | G12: 0.408 | H12: 0.405 | J12: 3yr avg FY2023-2025: 42.4%. Stabilizing at 41-42% after FY2022 spike. Base: gradual improvement as product mix shifts to higher-margin Crocs brand and franchise model expands. Upside: input cost deflation + pricing power. Downside: US tariff headwinds on manufacturing + raw material cost inflation. | K12: Crocs 10-K FY2024 p.53 | PitchBook Income Statement
B13: Upside | C13: 2 | D13: 0.405 | E13: 0.4 | F13: 0.395 | G13: 0.39 | H13: 0.385
B14: Downside | C14: 3 | D14: 0.425 | E14: 0.43 | F14: 0.435 | G14: 0.44 | H14: 0.44
B16: Active | D16: =D17 -> 0.35 | E16: =E17 -> 0.345 | F16: =F17 -> 0.34 | G16: =G17 -> 0.335 | H16: =H17 -> 0.33
A17: SG&A Expense (% of Revenue) | B17: Base | C17: 1 | D17: 0.35 | E17: 0.345 | F17: 0.34 | G17: 0.335 | H17: 0.33 | J17: Conservative base: FY2025 elevated at 35.5% due to HEYDUDE restructuring. Base case assumes only gradual improvement to 33% by 2030 given ongoing brand headwinds and tariff uncertainty. | K17: Crocs 10-K FY2025 p.53 | PitchBook Income Statement
B18: Upside | C18: 2 | D18: 0.34 | E18: 0.33 | F18: 0.32 | G18: 0.31 | H18: 0.3
B19: Downside | C19: 3 | D19: 0.36 | E19: 0.365 | F19: 0.37 | G19: 0.37 | H19: 0.37
B21: Active | D21: =D22 -> 0.02 | E21: =E22 -> 0.02 | F21: =F22 -> 0.02 | G21: =G22 -> 0.02 | H21: =H22 -> 0.02
A22: Depreciation & Amortization (% of Revenue, Total) | B22: Base | C22: 1 | D22: 0.02 | E22: 0.02 | F22: 0.02 | G22: 0.02 | H22: 0.02 | J22: IS D&A reflects depreciation of PP&E only (~0.9% revenue), consistent with Crocs 10-K where intangible amortization is captured within COGS/SG&A. Full D&A incl. amortization (~2.0% revenue) used in CFS and DCF addback. | K22: Crocs 10-K FY2025 p.55 | PitchBook Cash Flow Row 18
B23: Upside | C23: 2 | D23: 0.021 | E23: 0.021 | F23: 0.021 | G23: 0.021 | H23: 0.021
B24: Downside | C24: 3 | D24: 0.019 | E24: 0.019 | F24: 0.019 | G24: 0.019 | H24: 0.019
B26: Active | D26: =D27 -> 0.215 | E26: =E27 -> 0.215 | F26: =F27 -> 0.215 | G26: =G27 -> 0.215 | H26: =H27 -> 0.215
A27: Effective Tax Rate | B27: Base | C27: 1 | D27: 0.215 | E27: 0.215 | F27: 0.215 | G27: 0.215 | H27: 0.215 | J27: Base: US statutory rate 21.5% (GAAP guided rate). Upside: non-GAAP adjusted rate ~18% if international tax optimization. Downside: 23% if higher GAAP rate materializes per FY2026 guidance. | K27: Crocs 8-K FY2026 Guidance (Feb 2026): GAAP ~23%, Non-GAAP ~18% | US Tax Cuts & Jobs Act
B28: Upside | C28: 2 | D28: 0.18 | E28: 0.18 | F28: 0.18 | G28: 0.18 | H28: 0.18
B29: Downside | C29: 3 | D29: 0.23 | E29: 0.23 | F29: 0.23 | G29: 0.23 | H29: 0.23
A32: Basic Shares Reduction | D32: 0.02 | E32: 0.02 | F32: 0.02 | G32: 0.02 | H32: 0.02
A33: Diluted Shares | D33: 0.02 | E33: 0.02 | F33: 0.02 | G33: 0.02 | H33: 0.02
A35: Cash Flow Statement Assumptions
B36: Active | D36: =D37 -> 0.018 | E36: =E37 -> 0.018 | F36: =F37 -> 0.018 | G36: =G37 -> 0.018 | H36: =H37 -> 0.018
A37: Capital Expenditures (% of Revenue) | B37: Base | C37: 1 | D37: 0.018 | E37: 0.018 | F37: 0.018 | G37: 0.018 | H37: 0.018 | J37: FY2025 Capex dropped to 1.3% as company entered cost cutting mode. Management guided $70-80M for FY2026 vs ~$4B revenue = ~1.8%. Base: stable at guidance level. Upside: higher investment for expansion. Downside: further Capex cuts to preserve cash. | K37: Crocs 10-K FY2024 p.55 | Crocs 8-K Feb 2026 (Capex guidance $70-80M)
B38: Upside | C38: 2 | D38: 0.02 | E38: 0.02 | F38: 0.02 | G38: 0.02 | H38: 0.02
B39: Downside | C39: 3 | D39: 0.015 | E39: 0.015 | F39: 0.015 | G39: 0.015 | H39: 0.015
A41: Stock-Based Compensation (% of Revenue) | B41: Base | C41: 1 | D41: 0.008 | E41: 0.008 | F41: 0.008 | G41: 0.008 | H41: 0.008 | J41: Historical avg FY2022-2024: ~0.8%. Non-cash add-back in CFO. Relatively stable % of revenue. Upside: scale benefits dilute SBC. Downside: higher executive compensation. | K41: PitchBook Cash Flow Statement Row 20 | Crocs 10-K FY2024
B42: Upside | C42: 2 | D42: 0.007 | E42: 0.007 | F42: 0.007 | G42: 0.007 | H42: 0.007
B43: Downside | C43: 3 | D43: 0.009 | E43: 0.009 | F43: 0.009 | G43: 0.009 | H43: 0.009

Sheet Assumption 2
A1: Crocs, Inc. (CROX) – Assumptions Page 2: Balance Sheet / NWC
A2: Yellow = input | Base = Scenario 1 | Upside = Scenario 2 | Downside = Scenario 3 | Days unless stated
D3: Projection Period (FY2026E – FY2030E) | J3: Rationale | K3: Source
A4: Assumption | B4: Scenario | C4: # | D4: Year 1 2026E | E4: Year 2 2027E | F4: Year 3 2028E | G4: Year 4 2029E | H4: Year 5 2030E
A5: Balance Sheet / NWC Assumptions
B6: Active | D6: =D7 -> 29 | E6: =E7 -> 29 | F6: =F7 -> 29 | G6: =G7 -> 29 | H6: =H7 -> 29
A7: Days Sales Outstanding (DSO) | B7: Base | C7: 1 | D7: 29 | E7: 29 | F7: 29 | G7: 29 | H7: 29 | J7: 3yr avg FY2023-2025: 28.6 days. Fluctuating between 25-30 days. Base: stable at 3yr average. Upside: faster collections + growing DTC mix reduces receivables. Downside: slower collections under macro stress. | K7: Crocs 10-K FY2025 | PitchBook Balance Sheet (AR / Revenue × 365)
B8: Upside | C8: 2 | D8: 26.0 days | E8: 26 | F8: 26 | G8: 26 | H8: 26
B9: Downside | C9: 3 | D9: 32 | E9: 32 | F9: 32 | G9: 32 | H9: 32
B11: Active | D11: =D12 -> 79 | E11: =E12 -> 79 | F11: =F12 -> 79 | G11: =G12 -> 79 | H11: =H12 -> 79
A12: Days Inventory Held (DIH) | B12: Base | C12: 1 | D12: 79 | E12: 79 | F12: 79 | G12: 79 | H12: 79 | J12: 3yr avg FY2023-2025: 79.0 days. Relatively stable around 77-80 days. Base: stable at historical average. Upside: lean inventory management + strong demand reduces stock days. Downside: excess inventory buildup due to weak demand. | K12: Crocs 10-K FY2025 | PitchBook Balance Sheet (Inventory / COGS × 365)
B13: Upside | C13: 2 | D13: 74 | E13: 74 | F13: 74 | G13: 74 | H13: 74
B14: Downside | C14: 3 | D14: 84 | E14: 84 | F14: 84 | G14: 84 | H14: 84
B16: Active | D16: =D17 -> 77 | E16: =E17 -> 77 | F16: =F17 -> 77 | G16: =G17 -> 77 | H16: =H17 -> 77
A17: Days Payable Outstanding (DPO) | B17: Base | C17: 1 | D17: 77 | E17: 77 | F17: 77 | G17: 77 | H17: 77 | J17: 3yr avg FY2023-2025: 76.8 days. Fluctuating 73-84 days. Base: stable at 3yr average. Upside: stronger supplier relationships + extended payment terms. Downside: tighter supplier terms under financial stress. | K17: Crocs 10-K FY2025 | PitchBook Balance Sheet (AP / COGS × 365)
B18: Upside | C18: 2 | D18: 82 | E18: 82 | F18: 82 | G18: 82 | H18: 82
B19: Downside | C19: 3 | D19: 70 | E19: 70 | F19: 70 | G19: 70 | H19: 70
B21: Active | D21: =D22 -> 0.012 | E21: =E22 -> 0.012 | F21: =F22 -> 0.012 | G21: =G22 -> 0.012 | H21: =H22 -> 0.012
A22: Prepaid & Other (% of Revenue) | B22: Base | C22: 1 | D22: 0.012 | E22: 0.012 | F22: 0.012 | G22: 0.012 | H22: 0.012 | J22: 3yr avg FY2023-2025 stable. Base: stable at historical average. Upside: better cost control + efficient working capital management. Downside: higher accruals and liabilities under stressed conditions. | K22: Crocs 10-K FY2024 | PitchBook Balance Sheet
B23: Upside | C23: 2 | D23: 0.011 | E23: 0.011 | F23: 0.011 | G23: 0.011 | H23: 0.011
B24: Downside | C24: 3 | D24: 0.014 | E24: 0.014 | F24: 0.014 | G24: 0.014 | H24: 0.014
B26: Active | D26: =D27 -> 0.025 | E26: =E27 -> 0.025 | F26: =F27 -> 0.025 | G26: =G27 -> 0.025 | H26: =H27 -> 0.025
A27: Accrued Liabilities (% of Revenue) | B27: Base | C27: 1 | D27: 0.025 | E27: 0.025 | F27: 0.025 | G27: 0.025 | H27: 0.025 | J27: 3yr avg FY2023-2025 stable. Base: stable at historical average. Upside: better cost control + efficient working capital management. Downside: higher accruals and liabilities under stressed conditions. | K27: Crocs 10-K FY2024 | PitchBook Balance Sheet
B28: Upside | C28: 2 | D28: 0.022 | E28: 0.022 | F28: 0.022 | G28: 0.022 | H28: 0.022
B29: Downside | C29: 3 | D29: 0.028 | E29: 0.028 | F29: 0.028 | G29: 0.028 | H29: 0.028
B31: Active | D31: =D32 -> 0.023 | E31: =E32 -> 0.023 | F31: =F32 -> 0.023 | G31: =G32 -> 0.023 | H31: =H32 -> 0.023
A32: Other Current Liabilities (% of Revenue) | B32: Base | C32: 1 | D32: 0.023 | E32: 0.023 | F32: 0.023 | G32: 0.023 | H32: 0.023 | J32: 3yr avg FY2023-2025 stable. Base: stable at historical average. Upside: better cost control + efficient working capital management. Downside: higher accruals and liabilities under stressed conditions. | K32: Crocs 10-K FY2024 | PitchBook Balance Sheet
B33: Upside | C33: 2 | D33: 0.021 | E33: 0.021 | F33: 0.021 | G33: 0.021 | H33: 0.021
B34: Downside | C34: 3 | D34: 0.026 | E34: 0.026 | F34: 0.026 | G34: 0.026 | H34: 0.026

Sheet References
A1: References & Data Sources
A3: Reference / Source | B3: URL / Location
A4: Crocs, Inc. Form 10-K, FY2025 | B4: https://pitchbook.com
A5: Crocs, Inc. Form 10-K, FY2024 | B5: https://pitchbook.com
A6: Crocs, Inc. Form 10-K, FY2023 | B6: https://pitchbook.com
A7: Crocs, Inc. Form 10-K, FY2022 | B7: https://pitchbook.com
A8: Crocs, Inc. Form 10-K, FY2021 | B8: https://pitchbook.com
A9: Crocs, Inc. Form 10-K, FY2020 | B9: https://pitchbook.com
A10: Crocs, Inc. 8-K (Q4 / FY2025 Earnings Release & FY2026 Guidance) | B10: https://investors.crocs.com/news-releases
A11: PitchBook – Financial Data, Trading Multiples, Beta Data (CROX & Comps) | B11: https://pitchbook.com
A12: U.S. Treasury Daily Par Yield Curve Rates (10-yr: 4.44%) | B12: https://home.treasury.gov/resource-center/data-chart-center/interest-rates/
A13: Damodaran, Aswath – Implied Equity Risk Premium Update (4.46%) | B13: https://pages.stern.nyu.edu/~adamodar/
A14: Duff & Phelps / Kroll – 2024 SBBI Yearbook, Size Premium by Decile | B14: https://www.kroll.com/en/insights/publications/cost-of-capital
... A19: Crocs, Inc. Investor Relations – Press Releases & Presentations | B19: https://investors.crocs.com

Sheet AS1 Documentation
B1: Crocs, Inc. (CROX) — AS1 Assumption Documentation
B2: Income Statement & Cash Flow Assumptions | Historical analysis (FY2022–FY2024) | $ in thousands
B4: ① COGS % of Revenue | G4: ② SG&A % of Revenue
B5: Source: Income Statement → used to derive Gross Margin projection assumption | G5: Source: Income Statement → used to project operating expenses
B6: Year | C6: COGS ($K) | D6: Revenue ($K) | E6: COGS % | G6: Year | H6: SG&A ($K) | I6: Revenue ($K) | J6: SG&A %
B7: FY2022 | C7: 1694703 | D7: 3554985 | E7: 0.477 | G7: FY2022 | H7: 982706 | I7: 3554985 | J7: 0.276
B8: FY2023 | C8: 1752337 | D8: 3962347 | E8: 0.442 | G8: FY2023 | H8: 1151064 | I8: 3962347 | J8: 0.291
B9: FY2024 | C9: 1691850 | D9: 4102108 | E9: 0.412 | G9: FY2024 | H9: 1338032 | I9: 4102108 | J9: 0.326
B10: FY2025 | C10: 1683592 | D10: 4040647 | E10: 0.417 | G10: FY2025 | H10: 1435580 | I10: 4040647 | J10: 0.355
B11: 3-yr Avg (FY22–24) | E11: 0.444 | G11: 3-yr Avg (FY22–24) | J11: 0.298
B12: ↓ Declining trend — COGS % improving as Crocs brand mix shifts to higher-margin products. Base case assumes continued gradual improvement to 40.5% by FY2030. | G12: ↑ Increasing — driven by HEYDUDE restructuring costs & elevated marketing. Base case: gradual normalization to 33% by FY2030 as restructuring charges fade.
B15: ③ D&A % of Revenue (Total, from CFS) | G15: ④ Capital Expenditures % of Revenue
B16: Source: Cash Flow Statement → used for DCF addback & IS D&A projection | G16: Source: Cash Flow Statement → used to derive Unlevered FCF in DCF
B17: Year | C17: D&A ($K) | D17: Revenue ($K) | E17: D&A % | G17: Year | H17: Capex ($K) | I17: Revenue ($K) | J17: Capex %
B18: FY2022 | C18: 39229 | D18: 3554985 | E18: 0.011 | G18: FY2022 | H18: 104190 | I18: 3554985 | J18: 0.029
B19: FY2023 | C19: 54304 | D19: 3962347 | E19: 0.014 | G19: FY2023 | H19: 115625 | I19: 3962347 | J19: 0.029
B20: FY2024 | C20: 69840 | D20: 4102108 | E20: 0.017 | G20: FY2024 | H20: 169347 | I20: 4102108 | J20: 0.041
B21: FY2025 | C21: 79282 | D21: 4040647 | E21: 0.02 | G21: FY2025 | H21: 51365 | I21: 4040647 | J21: 0.013
B22: 3-yr Avg (FY22–24) | E22: 0.014 | G22: 3-yr Avg (FY22–24) | J22: 0.033
B23: ↑ Increasing — Capex investment driving higher depreciation. Note: IS D&A (~0.9% rev) differs from CFS D&A (~2.0%) as intangible amortization is captured in COGS/SG&A. Full 2.0% used in DCF addback. | G23: FY2024 spike from HEYDUDE integration. FY2025 dropped sharply to 1.3% (cost-cutting mode). Mgmt guided $70–80M for FY2026 (~1.8%). Base case: 1.8% stable. Source: Crocs 8-K Feb 2026.
B26: ⑤ Revenue Growth Rate — Historical Analysis & Projection Rationale
B27: Source: Crocs 10-K FY2020–FY2025, Crocs 8-K Feb 2026, Grand View Research (4.3% CAGR 2025–2030)
B28: Year | C28: Revenue ($K) | D28: YoY Growth | E28: Notes
B29: FY2020 | C29: 1385951 | D29: — | E29: COVID baseline — foam comfort surge begins
B30: FY2021 | C30: 2313416 | D30: 0.669 | E30: Post-COVID boom; DTC explosion
B31: FY2022 | C31: 3554985 | D31: 0.537 | E31: HEYDUDE acquisition ($2.5B); blended boost
B32: FY2023 | C32: 3962347 | D32: 0.115 | E32: Normalization; organic growth decelerating
B33: FY2024 | C33: 4102108 | D33: 0.035 | E33: Slow growth; HEYDUDE headwinds emerging
B34: FY2025 | C34: 4040647 | D34: -0.015 | E34: HEYDUDE down 14%; Crocs Brand +1.5%
B36: 3-yr CAGR (FY22–25) | C36: =(4040647/3554985)^(1/3)-1 -> 0.043608753 | E36: Excludes COVID distortion; used as baseline reference
B37: 2-yr CAGR (FY23–25) | C37: =(4040647/3962347)^(1/2)-1 -> 0.0098321719 | E37: Most recent trend; reflects deceleration phase
B38: Industry CAGR 2025–30 | C38: 0.043 | E38: Grand View Research global footwear market forecast
B39: Mgmt FY2026 Guidance | C39: 0% to (1%) | E39: Crocs 8-K Feb 2026 — conservative flat/decline
B41: Base Case Projection Rationale
B42: FY2026E | C42: -0.01 | E42: Per management guidance (flat to -1%). HEYDUDE trough year.
B43: FY2027E | C43: 0.01 | E43: Gradual recovery; HEYDUDE stabilizing; Crocs international +8%.
B44: FY2028E | C44: 0.025 | E44: Approaching industry CAGR; DTC channel gains momentum.
B45: FY2029E | C45: 0.035 | E45: Near industry CAGR; HEYDUDE contributing positively.
B46: FY2030E | C46: 0.043 | E46: Fully converged to Grand View Research industry CAGR of 4.3%.
B48: Why revenue recovers from FY2027+ | G48: Why recovery is conservative (Base case)
B49: • HEYDUDE bottoming out — strategic actions underway (SKU rationalisation, new brand president) | G49: • HEYDUDE turnaround uncertain — past guidance missed significantly
B50: • Crocs international +11% in FY2025 — Asia Pacific & EMEA expanding | G50: • US tariff headwinds on Vietnam/China manufacturing costs
B51: • DTC channel growing faster than wholesale, higher margins | G51: • North America consumer spending under pressure (rates, credit)
B52: • New product innovation — collab drops driving earned media | G52: • Strong USD hurting international revenues when converted back
B54: Sources: Crocs 10-K FY2020–FY2025 (SEC EDGAR) | Crocs 8-K Feb 2026 | Grand View Research Global Footwear Market 2025–2033 | PitchBook Financial Data
